verilog/modules/half_adder.v
`ifndef half_adder
`define half_adder
module half_adder(A,B,S,C);
    input A,B;
    output S,C;

    // S = A xor B
    cmos(S, A, ~B, B);
    cmos(S, ~A, B, ~B);

    and(C, A, B);
endmodule;


`endif

verilog/modules/full_adder.v
`include "../modules/half_adder.v"

module full_adder (A, B, C_in, S, C_out);
    input A,B,C_in;
    output S,C_out;
    wire s1,c1,c2;

    half_adder ha1(A,B,s1,c1);
    half_adder ha2(C_in,s1,S,c2);
    or(C_out,c1,c2);
endmodule;

verilog/modules/adder_8_bit.v
`include "../modules/full_adder.v"

module adder_8_bit(
    input [7:0] a,
    input [7:0] b,
    output [7:0] s,
    output c );

    wire [6:0] c_sub;

    half_adder ha1(a[0],b[0],s[0],c_sub[0]);
    full_adder fa1(a[1],b[1],c_sub[0],s[1],c_sub[1]);
    full_adder fa2(a[2],b[2],c_sub[1],s[2],c_sub[2]);
    full_adder fa3(a[3],b[3],c_sub[2],s[3],c_sub[3]);
    full_adder fa4(a[4],b[4],c_sub[3],s[4],c_sub[4]);
    full_adder fa5(a[5],b[5],c_sub[4],s[5],c_sub[5]);
    full_adder fa6(a[6],b[6],c_sub[5],s[6],c_sub[6]);
    full_adder fa7(a[7],b[7],c_sub[6],s[7],c);
endmodule;

verilog/tests/adder_8_bit_tb.v
`include "../modules/adder_8_bit.v"

module adder_8_bit_tb;
    reg [7:0] A = 0;
    reg [7:0] B = 0;
    wire [8:0] Sum;

    integer i;
    integer j;

    adder_8_bit adder(A,B,Sum[7:0],Sum[8]);

    initial begin;
        $dumpfile("../simulations/adder_8_bit_sim.vcd");
        $dumpvars(1, adder_8_bit_tb);

        for(i=0;i<256;i=i+1) begin;
            A = i; #1;
            for(j=0;j<256;j=j+1) begin;
                B = j; #1;
                if ((A+B)!=Sum) begin;
                    $monitor("%d + %d != %d", A, B, Sum);
                end;
            end;
        end;
    end;
endmodule;

verilog/simulations/adder_8_bit_sim.vcd
$date
	Tue Oct 24 12:09:12 2023
$end
$version
	Icarus Verilog
$end
$timescale
	1s
$end
$scope module adder_8_bit_tb $end
$var wire 9 ! Sum [8:0] $end
$var reg 8 " A [7:0] $end
$var reg 8 # B [7:0] $end
$var integer 32 $ i [31:0] $end
$var integer 32 % j [31:0] $end
$upscope $end
$enddefinitions $end
$comment Show the parameter values. $end
$dumpall
$end
#0
$dumpvars
bx %
b0 $
b0 #
b0 "
b0 !
$end
#1
b0 %
#2
b1 !
b1 #
b1 %
#3
b10 !
b10 #
b10 %
#4
b11 !
b11 #
b11 %
#5
b100 !
b100 #
b100 %
#6
b101 !
b101 #
b101 %
#7
b110 !
b110 #
b110 %
#8
b111 !
b111 #
b111 %
#9
b1000 !
b1000 #
b1000 %
#10
b1001 !
b1001 #
b1001 %
#11
b1010 !
b1010 #
b1010 %
#12
b1011 !
b1011 #
b1011 %
#13
b1100 !
b1100 #
b1100 %
#14
b1101 !
b1101 #
b1101 %
#15
b1110 !
b1110 #
b1110 %
#16
b1111 !
b1111 #
b1111 %
#17
b10000 !
b10000 #
b10000 %
#18
b10001 !
b10001 #
b10001 %
#19
b10010 !
b10010 #
b10010 %
#20
b10011 !
b10011 #
b10011 %
#21
b10100 !
b10100 #
b10100 %
#22
b10101 !
b10101 #
b10101 %
#23
b10110 !
b10110 #
b10110 %
#24
b10111 !
b10111 #
b10111 %
#25
b11000 !
b11000 #
b11000 %
#26
b11001 !
b11001 #
b11001 %
#27
b11010 !
b11010 #
b11010 %
#28
b11011 !
b11011 #
b11011 %
#29
b11100 !
b11100 #
b11100 %
#30
b11101 !
b11101 #
b11101 %
#31
b11110 !
b11110 #
b11110 %
#32
b11111 !
b11111 #
b11111 %
#33
b100000 !
b100000 #
b100000 %
#34
b100001 !
b100001 #
b100001 %
#35
b100010 !
b100010 #
b100010 %
#36
b100011 !
b100011 #
b100011 %
#37
b100100 !
b100100 #
b100100 %
#38
b100101 !
b100101 #
b100101 %
#39
b100110 !
b100110 #
b100110 %
#40
b100111 !
b100111 #
b100111 %
#41
b101000 !
b101000 #
b101000 %
#42
b101001 !
b101001 #
b101001 %
#43
b101010 !
b101010 #
b101010 %
#44
b101011 !
b101011 #
b101011 %
#45
b101100 !
b101100 #
b101100 %
#46
b101101 !
b101101 #
b101101 %
#47
b101110 !
b101110 #
b101110 %
#48
b101111 !
b101111 #
b101111 %
#49
b110000 !
b110000 #
b110000 %
#50
b110001 !
b110001 #
b110001 %
#51
b110010 !
b110010 #
b110010 %
#52
b110011 !
b110011 #
b110011 %
#53
b110100 !
b110100 #
b110100 %
#54
b110101 !
b110101 #
b110101 %
#55
b110110 !
b110110 #
b110110 %
#56
b110111 !
b110111 #
b110111 %
#57
b111000 !
b111000 #
b111000 %
#58
b111001 !
b111001 #
b111001 %
#59
b111010 !
b111010 #
b111010 %
#60
b111011 !
b111011 #
b111011 %
#61
b111100 !
b111100 #
b111100 %
#62
b111101 !
b111101 #
b111101 %
#63
b111110 !
b111110 #
b111110 %
#64
b111111 !
b111111 #
b111111 %
#65
b1000000 !
b1000000 #
b1000000 %
#66
b1000001 !
b1000001 #
b1000001 %
#67
b1000010 !
b1000010 #
b1000010 %
#68
b1000011 !
b1000011 #
b1000011 %
#69
b1000100 !
b1000100 #
b1000100 %
#70
b1000101 !
b1000101 #
b1000101 %
#71
b1000110 !
b1000110 #
b1000110 %
#72
b1000111 !
b1000111 #
b1000111 %
#73
b1001000 !
b1001000 #
b1001000 %
#74
b1001001 !
b1001001 #
b1001001 %
#75
b1001010 !
b1001010 #
b1001010 %
#76
b1001011 !
b1001011 #
b1001011 %
#77
b1001100 !
b1001100 #
b1001100 %
#78
b1001101 !
b1001101 #
b1001101 %
#79
b1001110 !
b1001110 #
b1001110 %
#80
b1001111 !
b1001111 #
b1001111 %
#81
b1010000 !
b1010000 #
b1010000 %
#82
b1010001 !
b1010001 #
b1010001 %
#83
b1010010 !
b1010010 #
b1010010 %
#84
b1010011 !
b1010011 #
b1010011 %
#85
b1010100 !
b1010100 #
b1010100 %
#86
b1010101 !
b1010101 #
b1010101 %
#87
b1010110 !
b1010110 #
b1010110 %
#88
b1010111 !
b1010111 #
b1010111 %
#89
b1011000 !
b1011000 #
b1011000 %
#90
b1011001 !
b1011001 #
b1011001 %
#91
b1011010 !
b1011010 #
b1011010 %
#92
b1011011 !
b1011011 #
b1011011 %
#93
b1011100 !
b1011100 #
b1011100 %
#94
b1011101 !
b1011101 #
b1011101 %
#95
b1011110 !
b1011110 #
b1011110 %
#96
b1011111 !
b1011111 #
b1011111 %
#97
b1100000 !
b1100000 #
b1100000 %
#98
b1100001 !
b1100001 #
b1100001 %
#99
b1100010 !
b1100010 #
b1100010 %
#100
b1100011 !
b1100011 #
b1100011 %
#101
b1100100 !
b1100100 #
b1100100 %
#102
b1100101 !
b1100101 #
b1100101 %
#103
b1100110 !
b1100110 #
b1100110 %
#104
b1100111 !
b1100111 #
b1100111 %
#105
b1101000 !
b1101000 #
b1101000 %
#106
b1101001 !
b1101001 #
b1101001 %
#107
b1101010 !
b1101010 #
b1101010 %
#108
b1101011 !
b1101011 #
b1101011 %
#109
b1101100 !
b1101100 #
b1101100 %
#110
b1101101 !
b1101101 #
b1101101 %
#111
b1101110 !
b1101110 #
b1101110 %
#112
b1101111 !
b1101111 #
b1101111 %
#113
b1110000 !
b1110000 #
b1110000 %
#114
b1110001 !
b1110001 #
b1110001 %
#115
b1110010 !
b1110010 #
b1110010 %
#116
b1110011 !
b1110011 #
b1110011 %
#117
b1110100 !
b1110100 #
b1110100 %
#118
b1110101 !
b1110101 #
b1110101 %
#119
b1110110 !
b1110110 #
b1110110 %
#120
b1110111 !
b1110111 #
b1110111 %
#121
b1111000 !
b1111000 #
b1111000 %
#122
b1111001 !
b1111001 #
b1111001 %
#123
b1111010 !
b1111010 #
b1111010 %
#124
b1111011 !
b1111011 #
b1111011 %
#125
b1111100 !
b1111100 #
b1111100 %
#126
b1111101 !
b1111101 #
b1111101 %
#127
b1111110 !
b1111110 #
b1111110 %
#128
b1111111 !
b1111111 #
b1111111 %
#129
b10000000 !
b10000000 #
b10000000 %
#130
b10000001 !
b10000001 #
b10000001 %
#131
b10000010 !
b10000010 #
b10000010 %
#132
b10000011 !
b10000011 #
b10000011 %
#133
b10000100 !
b10000100 #
b10000100 %
#134
b10000101 !
b10000101 #
b10000101 %
#135
b10000110 !
b10000110 #
b10000110 %
#136
b10000111 !
b10000111 #
b10000111 %
#137
b10001000 !
b10001000 #
b10001000 %
#138
b10001001 !
b10001001 #
b10001001 %
#139
b10001010 !
b10001010 #
b10001010 %
#140
b10001011 !
b10001011 #
b10001011 %
#141
b10001100 !
b10001100 #
b10001100 %
#142
b10001101 !
b10001101 #
b10001101 %
#143
b10001110 !
b10001110 #
b10001110 %
#144
b10001111 !
b10001111 #
b10001111 %
#145
b10010000 !
b10010000 #
b10010000 %
#146
b10010001 !
b10010001 #
b10010001 %
#147
b10010010 !
b10010010 #
b10010010 %
#148
b10010011 !
b10010011 #
b10010011 %
#149
b10010100 !
b10010100 #
b10010100 %
#150
b10010101 !
b10010101 #
b10010101 %
#151
b10010110 !
b10010110 #
b10010110 %
#152
b10010111 !
b10010111 #
b10010111 %
#153
b10011000 !
b10011000 #
b10011000 %
#154
b10011001 !
b10011001 #
b10011001 %
#155
b10011010 !
b10011010 #
b10011010 %
#156
b10011011 !
b10011011 #
b10011011 %
#157
b10011100 !
b10011100 #
b10011100 %
#158
b10011101 !
b10011101 #
b10011101 %
#159
b10011110 !
b10011110 #
b10011110 %
#160
b10011111 !
b10011111 #
b10011111 %
#161
b10100000 !
b10100000 #
b10100000 %
#162
b10100001 !
b10100001 #
b10100001 %
#163
b10100010 !
b10100010 #
b10100010 %
#164
b10100011 !
b10100011 #
b10100011 %
#165
b10100100 !
b10100100 #
b10100100 %
#166
b10100101 !
b10100101 #
b10100101 %
#167
b10100110 !
b10100110 #
b10100110 %
#168
b10100111 !
b10100111 #
b10100111 %
#169
b10101000 !
b10101000 #
b10101000 %
#170
b10101001 !
b10101001 #
b10101001 %
#171
b10101010 !
b10101010 #
b10101010 %
#172
b10101011 !
b10101011 #
b10101011 %
#173
b10101100 !
b10101100 #
b10101100 %
#174
b10101101 !
b10101101 #
b10101101 %
#175
b10101110 !
b10101110 #
b10101110 %
#176
b10101111 !
b10101111 #
b10101111 %
#177
b10110000 !
b10110000 #
b10110000 %
#178
b10110001 !
b10110001 #
b10110001 %
#179
b10110010 !
b10110010 #
b10110010 %
#180
b10110011 !
b10110011 #
b10110011 %
#181
b10110100 !
b10110100 #
b10110100 %
#182
b10110101 !
b10110101 #
b10110101 %
#183
b10110110 !
b10110110 #
b10110110 %
#184
b10110111 !
b10110111 #
b10110111 %
#185
b10111000 !
b10111000 #
b10111000 %
#186
b10111001 !
b10111001 #
b10111001 %
#187
b10111010 !
b10111010 #
b10111010 %
#188
b10111011 !
b10111011 #
b10111011 %
#189
b10111100 !
b10111100 #
b10111100 %
#190
b10111101 !
b10111101 #
b10111101 %
#191
b10111110 !
b10111110 #
b10111110 %
#192
b10111111 !
b10111111 #
b10111111 %
#193
b11000000 !
b11000000 #
b11000000 %
#194
b11000001 !
b11000001 #
b11000001 %
#195
b11000010 !
b11000010 #
b11000010 %
#196
b11000011 !
b11000011 #
b11000011 %
#197
b11000100 !
b11000100 #
b11000100 %
#198
b11000101 !
b11000101 #
b11000101 %
#199
b11000110 !
b11000110 #
b11000110 %
#200
b11000111 !
b11000111 #
b11000111 %
#201
b11001000 !
b11001000 #
b11001000 %
#202
b11001001 !
b11001001 #
b11001001 %
#203
b11001010 !
b11001010 #
b11001010 %
#204
b11001011 !
b11001011 #
b11001011 %
#205
b11001100 !
b11001100 #
b11001100 %
#206
b11001101 !
b11001101 #
b11001101 %
#207
b11001110 !
b11001110 #
b11001110 %
#208
b11001111 !
b11001111 #
b11001111 %
#209
b11010000 !
b11010000 #
b11010000 %
#210
b11010001 !
b11010001 #
b11010001 %
#211
b11010010 !
b11010010 #
b11010010 %
#212
b11010011 !
b11010011 #
b11010011 %
#213
b11010100 !
b11010100 #
b11010100 %
#214
b11010101 !
b11010101 #
b11010101 %
#215
b11010110 !
b11010110 #
b11010110 %
#216
b11010111 !
b11010111 #
b11010111 %
#217
b11011000 !
b11011000 #
b11011000 %
#218
b11011001 !
b11011001 #
b11011001 %
#219
b11011010 !
b11011010 #
b11011010 %
#220
b11011011 !
b11011011 #
b11011011 %
#221
b11011100 !
b11011100 #
b11011100 %
#222
b11011101 !
b11011101 #
b11011101 %
#223
b11011110 !
b11011110 #
b11011110 %
#224
b11011111 !
b11011111 #
b11011111 %
#225
b11100000 !
b11100000 #
b11100000 %
#226
b11100001 !
b11100001 #
b11100001 %
#227
b11100010 !
b11100010 #
b11100010 %
#228
b11100011 !
b11100011 #
b11100011 %
#229
b11100100 !
b11100100 #
b11100100 %
#230
b11100101 !
b11100101 #
b11100101 %
#231
b11100110 !
b11100110 #
b11100110 %
#232
b11100111 !
b11100111 #
b11100111 %
#233
b11101000 !
b11101000 #
b11101000 %
#234
b11101001 !
b11101001 #
b11101001 %
#235
b11101010 !
b11101010 #
b11101010 %
#236
b11101011 !
b11101011 #
b11101011 %
#237
b11101100 !
b11101100 #
b11101100 %
#238
b11101101 !
b11101101 #
b11101101 %
#239
b11101110 !
b11101110 #
b11101110 %
#240
b11101111 !
b11101111 #
b11101111 %
#241
b11110000 !
b11110000 #
b11110000 %
#242
b11110001 !
b11110001 #
b11110001 %
#243
b11110010 !
b11110010 #
b11110010 %
#244
b11110011 !
b11110011 #
b11110011 %
#245
b11110100 !
b11110100 #
b11110100 %
#246
b11110101 !
b11110101 #
b11110101 %
#247
b11110110 !
b11110110 #
b11110110 %
#248
b11110111 !
b11110111 #
b11110111 %
#249
b11111000 !
b11111000 #
b11111000 %
#250
b11111001 !
b11111001 #
b11111001 %
#251
b11111010 !
b11111010 #
b11111010 %
#252
b11111011 !
b11111011 #
b11111011 %
#253
b11111100 !
b11111100 #
b11111100 %
#254
b11111101 !
b11111101 #
b11111101 %
#255
b11111110 !
b11111110 #
b11111110 %
#256
b11111111 !
b11111111 #
b11111111 %
#257
b100000000 !
b1 "
b1 $
b100000000 %
#258
b1 !
b0 #
b0 %
#259
b10 !
b1 #
b1 %
#260
b11 !
b10 #
b10 %
#261
b100 !
b11 #
b11 %
#262
b101 !
b100 #
b100 %
#263
b110 !
b101 #
b101 %
#264
b111 !
b110 #
b110 %
#265
b1000 !
b111 #
b111 %
#266
b1001 !
b1000 #
b1000 %
#267
b1010 !
b1001 #
b1001 %
#268
b1011 !
b1010 #
b1010 %
#269
b1100 !
b1011 #
b1011 %
#270
b1101 !
b1100 #
b1100 %
#271
b1110 !
b1101 #
b1101 %
#272
b1111 !
b1110 #
b1110 %
#273
b10000 !
b1111 #
b1111 %
#274
b10001 !
b10000 #
b10000 %
#275
b10010 !
b10001 #
b10001 %
#276
b10011 !
b10010 #
b10010 %
#277
b10100 !
b10011 #
b10011 %
#278
b10101 !
b10100 #
b10100 %
#279
b10110 !
b10101 #
b10101 %
#280
b10111 !
b10110 #
b10110 %
#281
b11000 !
b10111 #
b10111 %
#282
b11001 !
b11000 #
b11000 %
#283
b11010 !
b11001 #
b11001 %
#284
b11011 !
b11010 #
b11010 %
#285
b11100 !
b11011 #
b11011 %
#286
b11101 !
b11100 #
b11100 %
#287
b11110 !
b11101 #
b11101 %
#288
b11111 !
b11110 #
b11110 %
#289
b100000 !
b11111 #
b11111 %
#290
b100001 !
b100000 #
b100000 %
#291
b100010 !
b100001 #
b100001 %
#292
b100011 !
b100010 #
b100010 %
#293
b100100 !
b100011 #
b100011 %
#294
b100101 !
b100100 #
b100100 %
#295
b100110 !
b100101 #
b100101 %
#296
b100111 !
b100110 #
b100110 %
#297
b101000 !
b100111 #
b100111 %
#298
b101001 !
b101000 #
b101000 %
#299
b101010 !
b101001 #
b101001 %
#300
b101011 !
b101010 #
b101010 %
#301
b101100 !
b101011 #
b101011 %
#302
b101101 !
b101100 #
b101100 %
#303
b101110 !
b101101 #
b101101 %
#304
b101111 !
b101110 #
b101110 %
#305
b110000 !
b101111 #
b101111 %
#306
b110001 !
b110000 #
b110000 %
#307
b110010 !
b110001 #
b110001 %
#308
b110011 !
b110010 #
b110010 %
#309
b110100 !
b110011 #
b110011 %
#310
b110101 !
b110100 #
b110100 %
#311
b110110 !
b110101 #
b110101 %
#312
b110111 !
b110110 #
b110110 %
#313
b111000 !
b110111 #
b110111 %
#314
b111001 !
b111000 #
b111000 %
#315
b111010 !
b111001 #
b111001 %
#316
b111011 !
b111010 #
b111010 %
#317
b111100 !
b111011 #
b111011 %
#318
b111101 !
b111100 #
b111100 %
#319
b111110 !
b111101 #
b111101 %
#320
b111111 !
b111110 #
b111110 %
#321
b1000000 !
b111111 #
b111111 %
#322
b1000001 !
b1000000 #
b1000000 %
#323
b1000010 !
b1000001 #
b1000001 %
#324
b1000011 !
b1000010 #
b1000010 %
#325
b1000100 !
b1000011 #
b1000011 %
#326
b1000101 !
b1000100 #
b1000100 %
#327
b1000110 !
b1000101 #
b1000101 %
#328
b1000111 !
b1000110 #
b1000110 %
#329
b1001000 !
b1000111 #
b1000111 %
#330
b1001001 !
b1001000 #
b1001000 %
#331
b1001010 !
b1001001 #
b1001001 %
#332
b1001011 !
b1001010 #
b1001010 %
#333
b1001100 !
b1001011 #
b1001011 %
#334
b1001101 !
b1001100 #
b1001100 %
#335
b1001110 !
b1001101 #
b1001101 %
#336
b1001111 !
b1001110 #
b1001110 %
#337
b1010000 !
b1001111 #
b1001111 %
#338
b1010001 !
b1010000 #
b1010000 %
#339
b1010010 !
b1010001 #
b1010001 %
#340
b1010011 !
b1010010 #
b1010010 %
#341
b1010100 !
b1010011 #
b1010011 %
#342
b1010101 !
b1010100 #
b1010100 %
#343
b1010110 !
b1010101 #
b1010101 %
#344
b1010111 !
b1010110 #
b1010110 %
#345
b1011000 !
b1010111 #
b1010111 %
#346
b1011001 !
b1011000 #
b1011000 %
#347
b1011010 !
b1011001 #
b1011001 %
#348
b1011011 !
b1011010 #
b1011010 %
#349
b1011100 !
b1011011 #
b1011011 %
#350
b1011101 !
b1011100 #
b1011100 %
#351
b1011110 !
b1011101 #
b1011101 %
#352
b1011111 !
b1011110 #
b1011110 %
#353
b1100000 !
b1011111 #
b1011111 %
#354
b1100001 !
b1100000 #
b1100000 %
#355
b1100010 !
b1100001 #
b1100001 %
#356
b1100011 !
b1100010 #
b1100010 %
#357
b1100100 !
b1100011 #
b1100011 %
#358
b1100101 !
b1100100 #
b1100100 %
#359
b1100110 !
b1100101 #
b1100101 %
#360
b1100111 !
b1100110 #
b1100110 %
#361
b1101000 !
b1100111 #
b1100111 %
#362
b1101001 !
b1101000 #
b1101000 %
#363
b1101010 !
b1101001 #
b1101001 %
#364
b1101011 !
b1101010 #
b1101010 %
#365
b1101100 !
b1101011 #
b1101011 %
#366
b1101101 !
b1101100 #
b1101100 %
#367
b1101110 !
b1101101 #
b1101101 %
#368
b1101111 !
b1101110 #
b1101110 %
#369
b1110000 !
b1101111 #
b1101111 %
#370
b1110001 !
b1110000 #
b1110000 %
#371
b1110010 !
b1110001 #
b1110001 %
#372
b1110011 !
b1110010 #
b1110010 %
#373
b1110100 !
b1110011 #
b1110011 %
#374
b1110101 !
b1110100 #
b1110100 %
#375
b1110110 !
b1110101 #
b1110101 %
#376
b1110111 !
b1110110 #
b1110110 %
#377
b1111000 !
b1110111 #
b1110111 %
#378
b1111001 !
b1111000 #
b1111000 %
#379
b1111010 !
b1111001 #
b1111001 %
#380
b1111011 !
b1111010 #
b1111010 %
#381
b1111100 !
b1111011 #
b1111011 %
#382
b1111101 !
b1111100 #
b1111100 %
#383
b1111110 !
b1111101 #
b1111101 %
#384
b1111111 !
b1111110 #
b1111110 %
#385
b10000000 !
b1111111 #
b1111111 %
#386
b10000001 !
b10000000 #
b10000000 %
#387
b10000010 !
b10000001 #
b10000001 %
#388
b10000011 !
b10000010 #
b10000010 %
#389
b10000100 !
b10000011 #
b10000011 %
#390
b10000101 !
b10000100 #
b10000100 %
#391
b10000110 !
b10000101 #
b10000101 %
#392
b10000111 !
b10000110 #
b10000110 %
#393
b10001000 !
b10000111 #
b10000111 %
#394
b10001001 !
b10001000 #
b10001000 %
#395
b10001010 !
b10001001 #
b10001001 %
#396
b10001011 !
b10001010 #
b10001010 %
#397
b10001100 !
b10001011 #
b10001011 %
#398
b10001101 !
b10001100 #
b10001100 %
#399
b10001110 !
b10001101 #
b10001101 %
#400
b10001111 !
b10001110 #
b10001110 %
#401
b10010000 !
b10001111 #
b10001111 %
#402
b10010001 !
b10010000 #
b10010000 %
#403
b10010010 !
b10010001 #
b10010001 %
#404
b10010011 !
b10010010 #
b10010010 %
#405
b10010100 !
b10010011 #
b10010011 %
#406
b10010101 !
b10010100 #
b10010100 %
#407
b10010110 !
b10010101 #
b10010101 %
#408
b10010111 !
b10010110 #
b10010110 %
#409
b10011000 !
b10010111 #
b10010111 %
#410
b10011001 !
b10011000 #
b10011000 %
#411
b10011010 !
b10011001 #
b10011001 %
#412
b10011011 !
b10011010 #
b10011010 %
#413
b10011100 !
b10011011 #
b10011011 %
#414
b10011101 !
b10011100 #
b10011100 %
#415
b10011110 !
b10011101 #
b10011101 %
#416
b10011111 !
b10011110 #
b10011110 %
#417
b10100000 !
b10011111 #
b10011111 %
#418
b10100001 !
b10100000 #
b10100000 %
#419
b10100010 !
b10100001 #
b10100001 %
#420
b10100011 !
b10100010 #
b10100010 %
#421
b10100100 !
b10100011 #
b10100011 %
#422
b10100101 !
b10100100 #
b10100100 %
#423
b10100110 !
b10100101 #
b10100101 %
#424
b10100111 !
b10100110 #
b10100110 %
#425
b10101000 !
b10100111 #
b10100111 %
#426
b10101001 !
b10101000 #
b10101000 %
#427
b10101010 !
b10101001 #
b10101001 %
#428
b10101011 !
b10101010 #
b10101010 %
#429
b10101100 !
b10101011 #
b10101011 %
#430
b10101101 !
b10101100 #
b10101100 %
#431
b10101110 !
b10101101 #
b10101101 %
#432
b10101111 !
b10101110 #
b10101110 %
#433
b10110000 !
b10101111 #
b10101111 %
#434
b10110001 !
b10110000 #
b10110000 %
#435
b10110010 !
b10110001 #
b10110001 %
#436
b10110011 !
b10110010 #
b10110010 %
#437
b10110100 !
b10110011 #
b10110011 %
#438
b10110101 !
b10110100 #
b10110100 %
#439
b10110110 !
b10110101 #
b10110101 %
#440
b10110111 !
b10110110 #
b10110110 %
#441
b10111000 !
b10110111 #
b10110111 %
#442
b10111001 !
b10111000 #
b10111000 %
#443
b10111010 !
b10111001 #
b10111001 %
#444
b10111011 !
b10111010 #
b10111010 %
#445
b10111100 !
b10111011 #
b10111011 %
#446
b10111101 !
b10111100 #
b10111100 %
#447
b10111110 !
b10111101 #
b10111101 %
#448
b10111111 !
b10111110 #
b10111110 %
#449
b11000000 !
b10111111 #
b10111111 %
#450
b11000001 !
b11000000 #
b11000000 %
#451
b11000010 !
b11000001 #
b11000001 %
#452
b11000011 !
b11000010 #
b11000010 %
#453
b11000100 !
b11000011 #
b11000011 %
#454
b11000101 !
b11000100 #
b11000100 %
#455
b11000110 !
b11000101 #
b11000101 %
#456
b11000111 !
b11000110 #
b11000110 %
#457
b11001000 !
b11000111 #
b11000111 %
#458
b11001001 !
b11001000 #
b11001000 %
#459
b11001010 !
b11001001 #
b11001001 %
#460
b11001011 !
b11001010 #
b11001010 %
#461
b11001100 !
b11001011 #
b11001011 %
#462
b11001101 !
b11001100 #
b11001100 %
#463
b11001110 !
b11001101 #
b11001101 %
#464
b11001111 !
b11001110 #
b11001110 %
#465
b11010000 !
b11001111 #
b11001111 %
#466
b11010001 !
b11010000 #
b11010000 %
#467
b11010010 !
b11010001 #
b11010001 %
#468
b11010011 !
b11010010 #
b11010010 %
#469
b11010100 !
b11010011 #
b11010011 %
#470
b11010101 !
b11010100 #
b11010100 %
#471
b11010110 !
b11010101 #
b11010101 %
#472
b11010111 !
b11010110 #
b11010110 %
#473
b11011000 !
b11010111 #
b11010111 %
#474
b11011001 !
b11011000 #
b11011000 %
#475
b11011010 !
b11011001 #
b11011001 %
#476
b11011011 !
b11011010 #
b11011010 %
#477
b11011100 !
b11011011 #
b11011011 %
#478
b11011101 !
b11011100 #
b11011100 %
#479
b11011110 !
b11011101 #
b11011101 %
#480
b11011111 !
b11011110 #
b11011110 %
#481
b11100000 !
b11011111 #
b11011111 %
#482
b11100001 !
b11100000 #
b11100000 %
#483
b11100010 !
b11100001 #
b11100001 %
#484
b11100011 !
b11100010 #
b11100010 %
#485
b11100100 !
b11100011 #
b11100011 %
#486
b11100101 !
b11100100 #
b11100100 %
#487
b11100110 !
b11100101 #
b11100101 %
#488
b11100111 !
b11100110 #
b11100110 %
#489
b11101000 !
b11100111 #
b11100111 %
#490
b11101001 !
b11101000 #
b11101000 %
#491
b11101010 !
b11101001 #
b11101001 %
#492
b11101011 !
b11101010 #
b11101010 %
#493
b11101100 !
b11101011 #
b11101011 %
#494
b11101101 !
b11101100 #
b11101100 %
#495
b11101110 !
b11101101 #
b11101101 %
#496
b11101111 !
b11101110 #
b11101110 %
#497
b11110000 !
b11101111 #
b11101111 %
#498
b11110001 !
b11110000 #
b11110000 %
#499
b11110010 !
b11110001 #
b11110001 %
#500
b11110011 !
b11110010 #
b11110010 %
#501
b11110100 !
b11110011 #
b11110011 %
#502
b11110101 !
b11110100 #
b11110100 %
#503
b11110110 !
b11110101 #
b11110101 %
#504
b11110111 !
b11110110 #
b11110110 %
#505
b11111000 !
b11110111 #
b11110111 %
#506
b11111001 !
b11111000 #
b11111000 %
#507
b11111010 !
b11111001 #
b11111001 %
#508
b11111011 !
b11111010 #
b11111010 %
#509
b11111100 !
b11111011 #
b11111011 %
#510
b11111101 !
b11111100 #
b11111100 %
#511
b11111110 !
b11111101 #
b11111101 %
#512
b11111111 !
b11111110 #
b11111110 %
#513
b100000000 !
b11111111 #
b11111111 %
#514
b100000001 !
b10 "
b10 $
b100000000 %
#515
b10 !
b0 #
b0 %
#516
b11 !
b1 #
b1 %
#517
b100 !
b10 #
b10 %
#518
b101 !
b11 #
b11 %
#519
b110 !
b100 #
b100 %
#520
b111 !
b101 #
b101 %
#521
b1000 !
b110 #
b110 %
#522
b1001 !
b111 #
b111 %
#523
b1010 !
b1000 #
b1000 %
#524
b1011 !
b1001 #
b1001 %
#525
b1100 !
b1010 #
b1010 %
#526
b1101 !
b1011 #
b1011 %
#527
b1110 !
b1100 #
b1100 %
#528
b1111 !
b1101 #
b1101 %
#529
b10000 !
b1110 #
b1110 %
#530
b10001 !
b1111 #
b1111 %
#531
b10010 !
b10000 #
b10000 %
#532
b10011 !
b10001 #
b10001 %
#533
b10100 !
b10010 #
b10010 %
#534
b10101 !
b10011 #
b10011 %
#535
b10110 !
b10100 #
b10100 %
#536
b10111 !
b10101 #
b10101 %
#537
b11000 !
b10110 #
b10110 %
#538
b11001 !
b10111 #
b10111 %
#539
b11010 !
b11000 #
b11000 %
#540
b11011 !
b11001 #
b11001 %
#541
b11100 !
b11010 #
b11010 %
#542
b11101 !
b11011 #
b11011 %
#543
b11110 !
b11100 #
b11100 %
#544
b11111 !
b11101 #
b11101 %
#545
b100000 !
b11110 #
b11110 %
#546
b100001 !
b11111 #
b11111 %
#547
b100010 !
b100000 #
b100000 %
#548
b100011 !
b100001 #
b100001 %
#549
b100100 !
b100010 #
b100010 %
#550
b100101 !
b100011 #
b100011 %
#551
b100110 !
b100100 #
b100100 %
#552
b100111 !
b100101 #
b100101 %
#553
b101000 !
b100110 #
b100110 %
#554
b101001 !
b100111 #
b100111 %
#555
b101010 !
b101000 #
b101000 %
#556
b101011 !
b101001 #
b101001 %
#557
b101100 !
b101010 #
b101010 %
#558
b101101 !
b101011 #
b101011 %
#559
b101110 !
b101100 #
b101100 %
#560
b101111 !
b101101 #
b101101 %
#561
b110000 !
b101110 #
b101110 %
#562
b110001 !
b101111 #
b101111 %
#563
b110010 !
b110000 #
b110000 %
#564
b110011 !
b110001 #
b110001 %
#565
b110100 !
b110010 #
b110010 %
#566
b110101 !
b110011 #
b110011 %
#567
b110110 !
b110100 #
b110100 %
#568
b110111 !
b110101 #
b110101 %
#569
b111000 !
b110110 #
b110110 %
#570
b111001 !
b110111 #
b110111 %
#571
b111010 !
b111000 #
b111000 %
#572
b111011 !
b111001 #
b111001 %
#573
b111100 !
b111010 #
b111010 %
#574
b111101 !
b111011 #
b111011 %
#575
b111110 !
b111100 #
b111100 %
#576
b111111 !
b111101 #
b111101 %
#577
b1000000 !
b111110 #
b111110 %
#578
b1000001 !
b111111 #
b111111 %
#579
b1000010 !
b1000000 #
b1000000 %
#580
b1000011 !
b1000001 #
b1000001 %
#581
b1000100 !
b1000010 #
b1000010 %
#582
b1000101 !
b1000011 #
b1000011 %
#583
b1000110 !
b1000100 #
b1000100 %
#584
b1000111 !
b1000101 #
b1000101 %
#585
b1001000 !
b1000110 #
b1000110 %
#586
b1001001 !
b1000111 #
b1000111 %
#587
b1001010 !
b1001000 #
b1001000 %
#588
b1001011 !
b1001001 #
b1001001 %
#589
b1001100 !
b1001010 #
b1001010 %
#590
b1001101 !
b1001011 #
b1001011 %
#591
b1001110 !
b1001100 #
b1001100 %
#592
b1001111 !
b1001101 #
b1001101 %
#593
b1010000 !
b1001110 #
b1001110 %
#594
b1010001 !
b1001111 #
b1001111 %
#595
b1010010 !
b1010000 #
b1010000 %
#596
b1010011 !
b1010001 #
b1010001 %
#597
b1010100 !
b1010010 #
b1010010 %
#598
b1010101 !
b1010011 #
b1010011 %
#599
b1010110 !
b1010100 #
b1010100 %
#600
b1010111 !
b1010101 #
b1010101 %
