verilog/modules/half_adder.v
module half_adder(A,B,S,C);
    input A,B;
    output S,C;

    // S = A xor B
    cmos(S, A, ~B, B);
    cmos(S, ~A, B, ~B);

    and(C, A, B);
endmodule;

verilog/modules/full_adder.v
`include "../modules/half_adder.v"

module full_adder (A, B, C_in, S, C_out);
    input A,B,C_in;
    output S,C_out;
    wire s1,c1,c2;

    half_adder ha1(A,B,s1,c1);
    half_adder ha2(C_in,s1,S,c2);
    or(C_out,c1,c2);
endmodule;

verilog/modules/adder_8_4_bit.v
`include "../modules/half_adder.v"
`include "../modules/full_adder.v"

`ifndef adder_8_4_bit
`define adder_8_4_bit

module adder_8_4_bit(
    input [7:0] A,
    input [3:0] B,
    output [7:0] S,
    output carry);

    wire [7:0] C;

    assign carry=C[7];

    half_adder add0(A[0],B[0],S[0],C[0]);
    full_adder add1(A[1],B[1],C[0],S[1],C[1]);
    full_adder add2(A[2],B[2],C[1],S[2],C[2]);
    full_adder add3(A[3],B[3],C[2],S[3],C[3]);
    half_adder add4(A[4],C[3],S[4],C[4]);
    half_adder add5(A[5],C[4],S[5],C[5]);
    half_adder add6(A[6],C[5],S[6],C[6]);
    half_adder add7(A[7],C[6],S[7],C[7]);

endmodule;

`endif

verilog/tests/adder_8_4_bit_tb.v
`include "../modules/adder_8_4_bit.v"

`ifndef adder_8_4_bit_tb
`define adder_8_4_bit_tb

module adder_8_4_bit_tb;

    reg [7:0] A;
    reg [3:0] B;

    wire [8:0] S;

    integer a = 0;
    integer b = 0;

    adder_8_4_bit add0(A,B,S[7:0],S[8]);

    initial begin;
        $dumpfile("../simulations/adder_8_4_bit_sim.vcd");
        $dumpvars(1, adder_8_4_bit_tb);

        for (a = 0; a < 256; a = a + 1) begin
            A = a;
            for (b = 0; b < 16; b = b + 1) begin
            B = b;
            #1;
            if ((A+B)!=S) begin;
                    $monitor("%d + %d != %d", A, B, S);
                end;  
            end;
        end;
    end;

endmodule;

`endif

verilog/simulations/adder_8_4_bit_sim.vcd
$date
	Wed Nov 15 12:12:38 2023
$end
$version
	Icarus Verilog
$end
$timescale
	1s
$end
$scope module adder_8_4_bit_tb $end
$var wire 9 ! S [8:0] $end
$var reg 8 " A [7:0] $end
$var reg 4 # B [3:0] $end
$var integer 32 $ a [31:0] $end
$var integer 32 % b [31:0] $end
$upscope $end
$enddefinitions $end
$comment Show the parameter values. $end
$dumpall
$end
#0
$dumpvars
b0 %
b0 $
b0 #
b0 "
b0 !
$end
#1
b1 !
b1 #
b1 %
#2
b10 !
b10 #
b10 %
#3
b11 !
b11 #
b11 %
#4
b100 !
b100 #
b100 %
#5
b101 !
b101 #
b101 %
#6
b110 !
b110 #
b110 %
#7
b111 !
b111 #
b111 %
#8
b1000 !
b1000 #
b1000 %
#9
b1001 !
b1001 #
b1001 %
#10
b1010 !
b1010 #
b1010 %
#11
b1011 !
b1011 #
b1011 %
#12
b1100 !
b1100 #
b1100 %
#13
b1101 !
b1101 #
b1101 %
#14
b1110 !
b1110 #
b1110 %
#15
b1111 !
b1111 #
b1111 %
#16
b1 !
b0 #
b1 "
b1 $
b0 %
#17
b10 !
b1 #
b1 %
#18
b11 !
b10 #
b10 %
#19
b100 !
b11 #
b11 %
#20
b101 !
b100 #
b100 %
#21
b110 !
b101 #
b101 %
#22
b111 !
b110 #
b110 %
#23
b1000 !
b111 #
b111 %
#24
b1001 !
b1000 #
b1000 %
#25
b1010 !
b1001 #
b1001 %
#26
b1011 !
b1010 #
b1010 %
#27
b1100 !
b1011 #
b1011 %
#28
b1101 !
b1100 #
b1100 %
#29
b1110 !
b1101 #
b1101 %
#30
b1111 !
b1110 #
b1110 %
#31
b10000 !
b1111 #
b1111 %
#32
b10 !
b0 #
b10 "
b10 $
b0 %
#33
b11 !
b1 #
b1 %
#34
b100 !
b10 #
b10 %
#35
b101 !
b11 #
b11 %
#36
b110 !
b100 #
b100 %
#37
b111 !
b101 #
b101 %
#38
b1000 !
b110 #
b110 %
#39
b1001 !
b111 #
b111 %
#40
b1010 !
b1000 #
b1000 %
#41
b1011 !
b1001 #
b1001 %
#42
b1100 !
b1010 #
b1010 %
#43
b1101 !
b1011 #
b1011 %
#44
b1110 !
b1100 #
b1100 %
#45
b1111 !
b1101 #
b1101 %
#46
b10000 !
b1110 #
b1110 %
#47
b10001 !
b1111 #
b1111 %
#48
b11 !
b0 #
b11 "
b11 $
b0 %
#49
b100 !
b1 #
b1 %
#50
b101 !
b10 #
b10 %
#51
b110 !
b11 #
b11 %
#52
b111 !
b100 #
b100 %
#53
b1000 !
b101 #
b101 %
#54
b1001 !
b110 #
b110 %
#55
b1010 !
b111 #
b111 %
#56
b1011 !
b1000 #
b1000 %
#57
b1100 !
b1001 #
b1001 %
#58
b1101 !
b1010 #
b1010 %
#59
b1110 !
b1011 #
b1011 %
#60
b1111 !
b1100 #
b1100 %
#61
b10000 !
b1101 #
b1101 %
#62
b10001 !
b1110 #
b1110 %
#63
b10010 !
b1111 #
b1111 %
#64
b100 !
b0 #
b100 "
b100 $
b0 %
#65
b101 !
b1 #
b1 %
#66
b110 !
b10 #
b10 %
#67
b111 !
b11 #
b11 %
#68
b1000 !
b100 #
b100 %
#69
b1001 !
b101 #
b101 %
#70
b1010 !
b110 #
b110 %
#71
b1011 !
b111 #
b111 %
#72
b1100 !
b1000 #
b1000 %
#73
b1101 !
b1001 #
b1001 %
#74
b1110 !
b1010 #
b1010 %
#75
b1111 !
b1011 #
b1011 %
#76
b10000 !
b1100 #
b1100 %
#77
b10001 !
b1101 #
b1101 %
#78
b10010 !
b1110 #
b1110 %
#79
b10011 !
b1111 #
b1111 %
#80
b101 !
b0 #
b101 "
b101 $
b0 %
#81
b110 !
b1 #
b1 %
#82
b111 !
b10 #
b10 %
#83
b1000 !
b11 #
b11 %
#84
b1001 !
b100 #
b100 %
#85
b1010 !
b101 #
b101 %
#86
b1011 !
b110 #
b110 %
#87
b1100 !
b111 #
b111 %
#88
b1101 !
b1000 #
b1000 %
#89
b1110 !
b1001 #
b1001 %
#90
b1111 !
b1010 #
b1010 %
#91
b10000 !
b1011 #
b1011 %
#92
b10001 !
b1100 #
b1100 %
#93
b10010 !
b1101 #
b1101 %
#94
b10011 !
b1110 #
b1110 %
#95
b10100 !
b1111 #
b1111 %
#96
b110 !
b0 #
b110 "
b110 $
b0 %
#97
b111 !
b1 #
b1 %
#98
b1000 !
b10 #
b10 %
#99
b1001 !
b11 #
b11 %
#100
b1010 !
b100 #
b100 %
#101
b1011 !
b101 #
b101 %
#102
b1100 !
b110 #
b110 %
#103
b1101 !
b111 #
b111 %
#104
b1110 !
b1000 #
b1000 %
#105
b1111 !
b1001 #
b1001 %
#106
b10000 !
b1010 #
b1010 %
#107
b10001 !
b1011 #
b1011 %
#108
b10010 !
b1100 #
b1100 %
#109
b10011 !
b1101 #
b1101 %
#110
b10100 !
b1110 #
b1110 %
#111
b10101 !
b1111 #
b1111 %
#112
b111 !
b0 #
b111 "
b111 $
b0 %
#113
b1000 !
b1 #
b1 %
#114
b1001 !
b10 #
b10 %
#115
b1010 !
b11 #
b11 %
#116
b1011 !
b100 #
b100 %
#117
b1100 !
b101 #
b101 %
#118
b1101 !
b110 #
b110 %
#119
b1110 !
b111 #
b111 %
#120
b1111 !
b1000 #
b1000 %
#121
b10000 !
b1001 #
b1001 %
#122
b10001 !
b1010 #
b1010 %
#123
b10010 !
b1011 #
b1011 %
#124
b10011 !
b1100 #
b1100 %
#125
b10100 !
b1101 #
b1101 %
#126
b10101 !
b1110 #
b1110 %
#127
b10110 !
b1111 #
b1111 %
#128
b1000 !
b0 #
b1000 "
b1000 $
b0 %
#129
b1001 !
b1 #
b1 %
#130
b1010 !
b10 #
b10 %
#131
b1011 !
b11 #
b11 %
#132
b1100 !
b100 #
b100 %
#133
b1101 !
b101 #
b101 %
#134
b1110 !
b110 #
b110 %
#135
b1111 !
b111 #
b111 %
#136
b10000 !
b1000 #
b1000 %
#137
b10001 !
b1001 #
b1001 %
#138
b10010 !
b1010 #
b1010 %
#139
b10011 !
b1011 #
b1011 %
#140
b10100 !
b1100 #
b1100 %
#141
b10101 !
b1101 #
b1101 %
#142
b10110 !
b1110 #
b1110 %
#143
b10111 !
b1111 #
b1111 %
#144
b1001 !
b0 #
b1001 "
b1001 $
b0 %
#145
b1010 !
b1 #
b1 %
#146
b1011 !
b10 #
b10 %
#147
b1100 !
b11 #
b11 %
#148
b1101 !
b100 #
b100 %
#149
b1110 !
b101 #
b101 %
#150
b1111 !
b110 #
b110 %
#151
b10000 !
b111 #
b111 %
#152
b10001 !
b1000 #
b1000 %
#153
b10010 !
b1001 #
b1001 %
#154
b10011 !
b1010 #
b1010 %
#155
b10100 !
b1011 #
b1011 %
#156
b10101 !
b1100 #
b1100 %
#157
b10110 !
b1101 #
b1101 %
#158
b10111 !
b1110 #
b1110 %
#159
b11000 !
b1111 #
b1111 %
#160
b1010 !
b0 #
b1010 "
b1010 $
b0 %
#161
b1011 !
b1 #
b1 %
#162
b1100 !
b10 #
b10 %
#163
b1101 !
b11 #
b11 %
#164
b1110 !
b100 #
b100 %
#165
b1111 !
b101 #
b101 %
#166
b10000 !
b110 #
b110 %
#167
b10001 !
b111 #
b111 %
#168
b10010 !
b1000 #
b1000 %
#169
b10011 !
b1001 #
b1001 %
#170
b10100 !
b1010 #
b1010 %
#171
b10101 !
b1011 #
b1011 %
#172
b10110 !
b1100 #
b1100 %
#173
b10111 !
b1101 #
b1101 %
#174
b11000 !
b1110 #
b1110 %
#175
b11001 !
b1111 #
b1111 %
#176
b1011 !
b0 #
b1011 "
b1011 $
b0 %
#177
b1100 !
b1 #
b1 %
#178
b1101 !
b10 #
b10 %
#179
b1110 !
b11 #
b11 %
#180
b1111 !
b100 #
b100 %
#181
b10000 !
b101 #
b101 %
#182
b10001 !
b110 #
b110 %
#183
b10010 !
b111 #
b111 %
#184
b10011 !
b1000 #
b1000 %
#185
b10100 !
b1001 #
b1001 %
#186
b10101 !
b1010 #
b1010 %
#187
b10110 !
b1011 #
b1011 %
#188
b10111 !
b1100 #
b1100 %
#189
b11000 !
b1101 #
b1101 %
#190
b11001 !
b1110 #
b1110 %
#191
b11010 !
b1111 #
b1111 %
#192
b1100 !
b0 #
b1100 "
b1100 $
b0 %
#193
b1101 !
b1 #
b1 %
#194
b1110 !
b10 #
b10 %
#195
b1111 !
b11 #
b11 %
#196
b10000 !
b100 #
b100 %
#197
b10001 !
b101 #
b101 %
#198
b10010 !
b110 #
b110 %
#199
b10011 !
b111 #
b111 %
#200
b10100 !
b1000 #
b1000 %
#201
b10101 !
b1001 #
b1001 %
#202
b10110 !
b1010 #
b1010 %
#203
b10111 !
b1011 #
b1011 %
#204
b11000 !
b1100 #
b1100 %
#205
b11001 !
b1101 #
b1101 %
#206
b11010 !
b1110 #
b1110 %
#207
b11011 !
b1111 #
b1111 %
#208
b1101 !
b0 #
b1101 "
b1101 $
b0 %
#209
b1110 !
b1 #
b1 %
#210
b1111 !
b10 #
b10 %
#211
b10000 !
b11 #
b11 %
#212
b10001 !
b100 #
b100 %
#213
b10010 !
b101 #
b101 %
#214
b10011 !
b110 #
b110 %
#215
b10100 !
b111 #
b111 %
#216
b10101 !
b1000 #
b1000 %
#217
b10110 !
b1001 #
b1001 %
#218
b10111 !
b1010 #
b1010 %
#219
b11000 !
b1011 #
b1011 %
#220
b11001 !
b1100 #
b1100 %
#221
b11010 !
b1101 #
b1101 %
#222
b11011 !
b1110 #
b1110 %
#223
b11100 !
b1111 #
b1111 %
#224
b1110 !
b0 #
b1110 "
b1110 $
b0 %
#225
b1111 !
b1 #
b1 %
#226
b10000 !
b10 #
b10 %
#227
b10001 !
b11 #
b11 %
#228
b10010 !
b100 #
b100 %
#229
b10011 !
b101 #
b101 %
#230
b10100 !
b110 #
b110 %
#231
b10101 !
b111 #
b111 %
#232
b10110 !
b1000 #
b1000 %
#233
b10111 !
b1001 #
b1001 %
#234
b11000 !
b1010 #
b1010 %
#235
b11001 !
b1011 #
b1011 %
#236
b11010 !
b1100 #
b1100 %
#237
b11011 !
b1101 #
b1101 %
#238
b11100 !
b1110 #
b1110 %
#239
b11101 !
b1111 #
b1111 %
#240
b1111 !
b0 #
b1111 "
b1111 $
b0 %
#241
b10000 !
b1 #
b1 %
#242
b10001 !
b10 #
b10 %
#243
b10010 !
b11 #
b11 %
#244
b10011 !
b100 #
b100 %
#245
b10100 !
b101 #
b101 %
#246
b10101 !
b110 #
b110 %
#247
b10110 !
b111 #
b111 %
#248
b10111 !
b1000 #
b1000 %
#249
b11000 !
b1001 #
b1001 %
#250
b11001 !
b1010 #
b1010 %
#251
b11010 !
b1011 #
b1011 %
#252
b11011 !
b1100 #
b1100 %
#253
b11100 !
b1101 #
b1101 %
#254
b11101 !
b1110 #
b1110 %
#255
b11110 !
b1111 #
b1111 %
#256
b10000 !
b0 #
b10000 "
b10000 $
b0 %
#257
b10001 !
b1 #
b1 %
#258
b10010 !
b10 #
b10 %
#259
b10011 !
b11 #
b11 %
#260
b10100 !
b100 #
b100 %
#261
b10101 !
b101 #
b101 %
#262
b10110 !
b110 #
b110 %
#263
b10111 !
b111 #
b111 %
#264
b11000 !
b1000 #
b1000 %
#265
b11001 !
b1001 #
b1001 %
#266
b11010 !
b1010 #
b1010 %
#267
b11011 !
b1011 #
b1011 %
#268
b11100 !
b1100 #
b1100 %
#269
b11101 !
b1101 #
b1101 %
#270
b11110 !
b1110 #
b1110 %
#271
b11111 !
b1111 #
b1111 %
#272
b10001 !
b0 #
b10001 "
b10001 $
b0 %
#273
b10010 !
b1 #
b1 %
#274
b10011 !
b10 #
b10 %
#275
b10100 !
b11 #
b11 %
#276
b10101 !
b100 #
b100 %
#277
b10110 !
b101 #
b101 %
#278
b10111 !
b110 #
b110 %
#279
b11000 !
b111 #
b111 %
#280
b11001 !
b1000 #
b1000 %
#281
b11010 !
b1001 #
b1001 %
#282
b11011 !
b1010 #
b1010 %
#283
b11100 !
b1011 #
b1011 %
#284
b11101 !
b1100 #
b1100 %
#285
b11110 !
b1101 #
b1101 %
#286
b11111 !
b1110 #
b1110 %
#287
b100000 !
b1111 #
b1111 %
#288
b10010 !
b0 #
b10010 "
b10010 $
b0 %
#289
b10011 !
b1 #
b1 %
#290
b10100 !
b10 #
b10 %
#291
b10101 !
b11 #
b11 %
#292
b10110 !
b100 #
b100 %
#293
b10111 !
b101 #
b101 %
#294
b11000 !
b110 #
b110 %
#295
b11001 !
b111 #
b111 %
#296
b11010 !
b1000 #
b1000 %
#297
b11011 !
b1001 #
b1001 %
#298
b11100 !
b1010 #
b1010 %
#299
b11101 !
b1011 #
b1011 %
#300
b11110 !
b1100 #
b1100 %
#301
b11111 !
b1101 #
b1101 %
#302
b100000 !
b1110 #
b1110 %
#303
b100001 !
b1111 #
b1111 %
#304
b10011 !
b0 #
b10011 "
b10011 $
b0 %
#305
b10100 !
b1 #
b1 %
#306
b10101 !
b10 #
b10 %
#307
b10110 !
b11 #
b11 %
#308
b10111 !
b100 #
b100 %
#309
b11000 !
b101 #
b101 %
#310
b11001 !
b110 #
b110 %
#311
b11010 !
b111 #
b111 %
#312
b11011 !
b1000 #
b1000 %
#313
b11100 !
b1001 #
b1001 %
#314
b11101 !
b1010 #
b1010 %
#315
b11110 !
b1011 #
b1011 %
#316
b11111 !
b1100 #
b1100 %
#317
b100000 !
b1101 #
b1101 %
#318
b100001 !
b1110 #
b1110 %
#319
b100010 !
b1111 #
b1111 %
#320
b10100 !
b0 #
b10100 "
b10100 $
b0 %
#321
b10101 !
b1 #
b1 %
#322
b10110 !
b10 #
b10 %
#323
b10111 !
b11 #
b11 %
#324
b11000 !
b100 #
b100 %
#325
b11001 !
b101 #
b101 %
#326
b11010 !
b110 #
b110 %
#327
b11011 !
b111 #
b111 %
#328
b11100 !
b1000 #
b1000 %
#329
b11101 !
b1001 #
b1001 %
#330
b11110 !
b1010 #
b1010 %
#331
b11111 !
b1011 #
b1011 %
#332
b100000 !
b1100 #
b1100 %
#333
b100001 !
b1101 #
b1101 %
#334
b100010 !
b1110 #
b1110 %
#335
b100011 !
b1111 #
b1111 %
#336
b10101 !
b0 #
b10101 "
b10101 $
b0 %
#337
b10110 !
b1 #
b1 %
#338
b10111 !
b10 #
b10 %
#339
b11000 !
b11 #
b11 %
#340
b11001 !
b100 #
b100 %
#341
b11010 !
b101 #
b101 %
#342
b11011 !
b110 #
b110 %
#343
b11100 !
b111 #
b111 %
#344
b11101 !
b1000 #
b1000 %
#345
b11110 !
b1001 #
b1001 %
#346
b11111 !
b1010 #
b1010 %
#347
b100000 !
b1011 #
b1011 %
#348
b100001 !
b1100 #
b1100 %
#349
b100010 !
b1101 #
b1101 %
#350
b100011 !
b1110 #
b1110 %
#351
b100100 !
b1111 #
b1111 %
#352
b10110 !
b0 #
b10110 "
b10110 $
b0 %
#353
b10111 !
b1 #
b1 %
#354
b11000 !
b10 #
b10 %
#355
b11001 !
b11 #
b11 %
#356
b11010 !
b100 #
b100 %
#357
b11011 !
b101 #
b101 %
#358
b11100 !
b110 #
b110 %
#359
b11101 !
b111 #
b111 %
#360
b11110 !
b1000 #
b1000 %
#361
b11111 !
b1001 #
b1001 %
#362
b100000 !
b1010 #
b1010 %
#363
b100001 !
b1011 #
b1011 %
#364
b100010 !
b1100 #
b1100 %
#365
b100011 !
b1101 #
b1101 %
#366
b100100 !
b1110 #
b1110 %
#367
b100101 !
b1111 #
b1111 %
#368
b10111 !
b0 #
b10111 "
b10111 $
b0 %
#369
b11000 !
b1 #
b1 %
#370
b11001 !
b10 #
b10 %
#371
b11010 !
b11 #
b11 %
#372
b11011 !
b100 #
b100 %
#373
b11100 !
b101 #
b101 %
#374
b11101 !
b110 #
b110 %
#375
b11110 !
b111 #
b111 %
#376
b11111 !
b1000 #
b1000 %
#377
b100000 !
b1001 #
b1001 %
#378
b100001 !
b1010 #
b1010 %
#379
b100010 !
b1011 #
b1011 %
#380
b100011 !
b1100 #
b1100 %
#381
b100100 !
b1101 #
b1101 %
#382
b100101 !
b1110 #
b1110 %
#383
b100110 !
b1111 #
b1111 %
#384
b11000 !
b0 #
b11000 "
b11000 $
b0 %
#385
b11001 !
b1 #
b1 %
#386
b11010 !
b10 #
b10 %
#387
b11011 !
b11 #
b11 %
#388
b11100 !
b100 #
b100 %
#389
b11101 !
b101 #
b101 %
#390
b11110 !
b110 #
b110 %
#391
b11111 !
b111 #
b111 %
#392
b100000 !
b1000 #
b1000 %
#393
b100001 !
b1001 #
b1001 %
#394
b100010 !
b1010 #
b1010 %
#395
b100011 !
b1011 #
b1011 %
#396
b100100 !
b1100 #
b1100 %
#397
b100101 !
b1101 #
b1101 %
#398
b100110 !
b1110 #
b1110 %
#399
b100111 !
b1111 #
b1111 %
#400
b11001 !
b0 #
b11001 "
b11001 $
b0 %
#401
b11010 !
b1 #
b1 %
#402
b11011 !
b10 #
b10 %
#403
b11100 !
b11 #
b11 %
#404
b11101 !
b100 #
b100 %
#405
b11110 !
b101 #
b101 %
#406
b11111 !
b110 #
b110 %
#407
b100000 !
b111 #
b111 %
#408
b100001 !
b1000 #
b1000 %
#409
b100010 !
b1001 #
b1001 %
#410
b100011 !
b1010 #
b1010 %
#411
b100100 !
b1011 #
b1011 %
#412
b100101 !
b1100 #
b1100 %
#413
b100110 !
b1101 #
b1101 %
#414
b100111 !
b1110 #
b1110 %
#415
b101000 !
b1111 #
b1111 %
#416
b11010 !
b0 #
b11010 "
b11010 $
b0 %
#417
b11011 !
b1 #
b1 %
#418
b11100 !
b10 #
b10 %
#419
b11101 !
b11 #
b11 %
#420
b11110 !
b100 #
b100 %
#421
b11111 !
b101 #
b101 %
#422
b100000 !
b110 #
b110 %
#423
b100001 !
b111 #
b111 %
#424
b100010 !
b1000 #
b1000 %
#425
b100011 !
b1001 #
b1001 %
#426
b100100 !
b1010 #
b1010 %
#427
b100101 !
b1011 #
b1011 %
#428
b100110 !
b1100 #
b1100 %
#429
b100111 !
b1101 #
b1101 %
#430
b101000 !
b1110 #
b1110 %
#431
b101001 !
b1111 #
b1111 %
#432
b11011 !
b0 #
b11011 "
b11011 $
b0 %
#433
b11100 !
b1 #
b1 %
#434
b11101 !
b10 #
b10 %
#435
b11110 !
b11 #
b11 %
#436
b11111 !
b100 #
b100 %
#437
b100000 !
b101 #
b101 %
#438
b100001 !
b110 #
b110 %
#439
b100010 !
b111 #
b111 %
#440
b100011 !
b1000 #
b1000 %
#441
b100100 !
b1001 #
b1001 %
#442
b100101 !
b1010 #
b1010 %
#443
b100110 !
b1011 #
b1011 %
#444
b100111 !
b1100 #
b1100 %
#445
b101000 !
b1101 #
b1101 %
#446
b101001 !
b1110 #
b1110 %
#447
b101010 !
b1111 #
b1111 %
#448
b11100 !
b0 #
b11100 "
b11100 $
b0 %
#449
b11101 !
b1 #
b1 %
#450
b11110 !
b10 #
b10 %
#451
b11111 !
b11 #
b11 %
#452
b100000 !
b100 #
b100 %
#453
b100001 !
b101 #
b101 %
#454
b100010 !
b110 #
b110 %
#455
b100011 !
b111 #
b111 %
#456
b100100 !
b1000 #
b1000 %
#457
b100101 !
b1001 #
b1001 %
#458
b100110 !
b1010 #
b1010 %
#459
b100111 !
b1011 #
b1011 %
#460
b101000 !
b1100 #
b1100 %
#461
b101001 !
b1101 #
b1101 %
#462
b101010 !
b1110 #
b1110 %
#463
b101011 !
b1111 #
b1111 %
#464
b11101 !
b0 #
b11101 "
b11101 $
b0 %
#465
b11110 !
b1 #
b1 %
#466
b11111 !
b10 #
b10 %
#467
b100000 !
b11 #
b11 %
#468
b100001 !
b100 #
b100 %
#469
b100010 !
b101 #
b101 %
#470
b100011 !
b110 #
b110 %
#471
b100100 !
b111 #
b111 %
#472
b100101 !
b1000 #
b1000 %
#473
b100110 !
b1001 #
b1001 %
#474
b100111 !
b1010 #
b1010 %
#475
b101000 !
b1011 #
b1011 %
#476
b101001 !
b1100 #
b1100 %
#477
b101010 !
b1101 #
b1101 %
#478
b101011 !
b1110 #
b1110 %
#479
b101100 !
b1111 #
b1111 %
#480
b11110 !
b0 #
b11110 "
b11110 $
b0 %
#481
b11111 !
b1 #
b1 %
#482
b100000 !
b10 #
b10 %
#483
b100001 !
b11 #
b11 %
#484
b100010 !
b100 #
b100 %
#485
b100011 !
b101 #
b101 %
#486
b100100 !
b110 #
b110 %
#487
b100101 !
b111 #
b111 %
#488
b100110 !
b1000 #
b1000 %
#489
b100111 !
b1001 #
b1001 %
#490
b101000 !
b1010 #
b1010 %
#491
b101001 !
b1011 #
b1011 %
#492
b101010 !
b1100 #
b1100 %
#493
b101011 !
b1101 #
b1101 %
#494
b101100 !
b1110 #
b1110 %
#495
b101101 !
b1111 #
b1111 %
#496
b11111 !
b0 #
b11111 "
b11111 $
b0 %
#497
b100000 !
b1 #
b1 %
#498
b100001 !
b10 #
b10 %
#499
b100010 !
b11 #
b11 %
#500
b100011 !
b100 #
b100 %
#501
b100100 !
b101 #
b101 %
#502
b100101 !
b110 #
b110 %
#503
b100110 !
b111 #
b111 %
#504
b100111 !
b1000 #
b1000 %
#505
b101000 !
b1001 #
b1001 %
#506
b101001 !
b1010 #
b1010 %
#507
b101010 !
b1011 #
b1011 %
#508
b101011 !
b1100 #
b1100 %
#509
b101100 !
b1101 #
b1101 %
#510
b101101 !
b1110 #
b1110 %
#511
b101110 !
b1111 #
b1111 %
#512
b100000 !
b0 #
b100000 "
b100000 $
b0 %
#513
b100001 !
b1 #
b1 %
#514
b100010 !
b10 #
b10 %
#515
b100011 !
b11 #
b11 %
#516
b100100 !
b100 #
b100 %
#517
b100101 !
b101 #
b101 %
#518
b100110 !
b110 #
b110 %
#519
b100111 !
b111 #
b111 %
#520
b101000 !
b1000 #
b1000 %
#521
b101001 !
b1001 #
b1001 %
#522
b101010 !
b1010 #
b1010 %
#523
b101011 !
b1011 #
b1011 %
#524
b101100 !
b1100 #
b1100 %
#525
b101101 !
b1101 #
b1101 %
#526
b101110 !
b1110 #
b1110 %
#527
b101111 !
b1111 #
b1111 %
#528
b100001 !
b0 #
b100001 "
b100001 $
b0 %
#529
b100010 !
b1 #
b1 %
#530
b100011 !
b10 #
b10 %
#531
b100100 !
b11 #
b11 %
#532
b100101 !
b100 #
b100 %
#533
b100110 !
b101 #
b101 %
#534
b100111 !
b110 #
b110 %
#535
b101000 !
b111 #
b111 %
#536
b101001 !
b1000 #
b1000 %
#537
b101010 !
b1001 #
b1001 %
#538
b101011 !
b1010 #
b1010 %
#539
b101100 !
b1011 #
b1011 %
#540
b101101 !
b1100 #
b1100 %
#541
b101110 !
b1101 #
b1101 %
#542
b101111 !
b1110 #
b1110 %
#543
b110000 !
b1111 #
b1111 %
#544
b100010 !
b0 #
b100010 "
b100010 $
b0 %
#545
b100011 !
b1 #
b1 %
#546
b100100 !
b10 #
b10 %
#547
b100101 !
b11 #
b11 %
#548
b100110 !
b100 #
b100 %
#549
b100111 !
b101 #
b101 %
#550
b101000 !
b110 #
b110 %
#551
b101001 !
b111 #
b111 %
#552
b101010 !
b1000 #
b1000 %
#553
b101011 !
b1001 #
b1001 %
#554
b101100 !
b1010 #
b1010 %
#555
b101101 !
b1011 #
b1011 %
#556
b101110 !
b1100 #
b1100 %
#557
b101111 !
b1101 #
b1101 %
#558
b110000 !
b1110 #
b1110 %
#559
b110001 !
b1111 #
b1111 %
#560
b100011 !
b0 #
b100011 "
b100011 $
b0 %
#561
b100100 !
b1 #
b1 %
#562
b100101 !
b10 #
b10 %
#563
b100110 !
b11 #
b11 %
#564
b100111 !
b100 #
b100 %
#565
b101000 !
b101 #
b101 %
#566
b101001 !
b110 #
b110 %
#567
b101010 !
b111 #
b111 %
#568
b101011 !
b1000 #
b1000 %
#569
b101100 !
b1001 #
b1001 %
#570
b101101 !
b1010 #
b1010 %
#571
b101110 !
b1011 #
b1011 %
#572
b101111 !
b1100 #
b1100 %
#573
b110000 !
b1101 #
b1101 %
#574
b110001 !
b1110 #
b1110 %
#575
b110010 !
b1111 #
b1111 %
#576
b100100 !
b0 #
b100100 "
b100100 $
b0 %
#577
b100101 !
b1 #
b1 %
#578
b100110 !
b10 #
b10 %
#579
b100111 !
b11 #
b11 %
#580
b101000 !
b100 #
b100 %
#581
b101001 !
b101 #
b101 %
#582
b101010 !
b110 #
b110 %
#583
b101011 !
b111 #
b111 %
#584
b101100 !
b1000 #
b1000 %
#585
b101101 !
b1001 #
b1001 %
#586
b101110 !
b1010 #
b1010 %
#587
b101111 !
b1011 #
b1011 %
#588
b110000 !
b1100 #
b1100 %
#589
b110001 !
b1101 #
b1101 %
#590
b110010 !
b1110 #
b1110 %
#591
b110011 !
b1111 #
b1111 %
#592
b100101 !
b0 #
b100101 "
b100101 $
b0 %
#593
b100110 !
b1 #
b1 %
#594
b100111 !
b10 #
b10 %
#595
b101000 !
b11 #
b11 %
#596
b101001 !
b100 #
b100 %
#597
b101010 !
b101 #
b101 %
#598
b101011 !
b110 #
b110 %
#599
b101100 !
b111 #
b111 %
#600
b101101 !
b1000 #
b1000 %
#601
b101110 !
b1001 #
b1001 %
#602
b101111 !
b1010 #
b1010 %
#603
b110000 !
b1011 #
b1011 %
#604
b110001 !
b1100 #
b1100 %
#605
b110010 !
b1101 #
b1101 %
#606
b110011 !
b1110 #
b1110 %
#607
b110100 !
b1111 #
b1111 %
#608
b100110 !
b0 #
b100110 "
b100110 $
b0 %
#609
b100111 !
b1 #
b1 %
#610
b101000 !
b10 #
b10 %
#611
b101001 !
b11 #
b11 %
#612
b101010 !
b100 #
b100 %
#613
b101011 !
b101 #
b101 %
#614
b101100 !
b110 #
b110 %
#615
b101101 !
b111 #
b111 %
#616
b101110 !
b1000 #
b1000 %
#617
b101111 !
b1001 #
b1001 %
#618
b110000 !
b1010 #
b1010 %
#619
b110001 !
b1011 #
b1011 %
#620
b110010 !
b1100 #
b1100 %
#621
b110011 !
b1101 #
b1101 %
#622
b110100 !
b1110 #
b1110 %
#623
b110101 !
b1111 #
b1111 %
#624
b100111 !
b0 #
b100111 "
b100111 $
b0 %
#625
b101000 !
b1 #
b1 %
#626
b101001 !
b10 #
b10 %
#627
b101010 !
b11 #
b11 %
#628
b101011 !
b100 #
b100 %
#629
b101100 !
b101 #
b101 %
#630
b101101 !
b110 #
b110 %
#631
b101110 !
b111 #
b111 %
#632
b101111 !
b1000 #
b1000 %
#633
b110000 !
b1001 #
b1001 %
#634
b110001 !
b1010 #
b1010 %
#635
b110010 !
b1011 #
b1011 %
#636
b110011 !
b1100 #
b1100 %
#637
b110100 !
b1101 #
b1101 %
#638
b110101 !
b1110 #
b1110 %
#639
b110110 !
b1111 #
b1111 %
#640
b101000 !
b0 #
b101000 "
b101000 $
b0 %
#641
b101001 !
b1 #
b1 %
#642
b101010 !
b10 #
b10 %
#643
b101011 !
b11 #
b11 %
#644
b101100 !
b100 #
b100 %
#645
b101101 !
b101 #
b101 %
#646
b101110 !
b110 #
b110 %
#647
b101111 !
b111 #
b111 %
#648
b110000 !
b1000 #
b1000 %
#649
b110001 !
b1001 #
b1001 %
#650
b110010 !
b1010 #
b1010 %
#651
b110011 !
b1011 #
b1011 %
#652
b110100 !
b1100 #
b1100 %
#653
b110101 !
b1101 #
b1101 %
#654
b110110 !
b1110 #
b1110 %
#655
b110111 !
b1111 #
b1111 %
#656
b101001 !
b0 #
b101001 "
b101001 $
b0 %
#657
b101010 !
b1 #
b1 %
#658
b101011 !
b10 #
b10 %
#659
b101100 !
b11 #
b11 %
#660
b101101 !
b100 #
b100 %
#661
b101110 !
b101 #
b101 %
#662
b101111 !
b110 #
b110 %
#663
b110000 !
b111 #
b111 %
#664
b110001 !
b1000 #
b1000 %
#665
b110010 !
b1001 #
b1001 %
