verilog/modules/d_latch.v
module d_latch(
    input in,
    input clk,
    input clk_bar,
    output Q,
    output Q_bar);

    wire clk_bar,w;

    not(w,Q_bar);
    not(Q_bar,Q);
    cmos(Q,in,clk,clk_bar);
    cmos(Q,w,clk_bar,clk);
endmodule;

verilog/tests/d_latch_tb.v
`include "../modules/d_latch.v"

module d_latch_tb;

    reg a = 0;
    reg clk = 0;
    wire q;
    wire q_bar;

    d_latch d(a,clk,~clk,q,q_bar);

    initial begin;
        $dumpfile("../simulations/d_latch_sim.vcd");
        $dumpvars(1,d_latch_tb);

        wait(~clk) begin
            a = 1;
        end;
        wait(clk) begin
            #1;
            #1;
            #1;
            a = 0;
            #1;
            a = 1;
            #1; 
            a = 0;
            #1;
            a = 1;
        end;
        wait(~clk) begin
            #1;
            a = 0;
            #1;
            a = 1;
            #1; 
            a = 0;
            #1;
            #10;
        end;
        $finish;
    end;
    always #10 clk = ~clk;
endmodule;

verilog/simulations/d_latch_sim.vcd
$date
	Tue Oct 24 14:01:38 2023
$end
$version
	Icarus Verilog
$end
$timescale
	1s
$end
$scope module d_latch_tb $end
$var wire 1 ! q_bar $end
$var wire 1 " q $end
$var reg 1 # a $end
$var reg 1 $ clk $end
$upscope $end
$enddefinitions $end
$comment Show the parameter values. $end
$dumpall
$end
#0
$dumpvars
0$
1#
x"
x!
$end
#10
0!
1"
1$
#13
1!
0"
0#
#14
0!
1"
1#
#15
1!
0"
0#
#16
0!
1"
1#
#20
0$
#21
0#
#22
1#
#23
0#
#30
1!
0"
1$
