verilog/modules/full_adder.v
`include "../modules/half_adder.v"

module full_adder (A, B, C_in, S, C_out);
    input A,B,C_in;
    output S,C_out;
    wire s1,c1,c2;

    half_adder ha1(A,B,s1,c1);
    half_adder ha2(C_in,s1,S,c2);
    or(C_out,c1,c2);
endmodule;

verilog/modules/d_latch.v
module d_latch(
    input in,
    input clk,
    input clk_bar,
    output Q,
    output Q_bar);

    wire clk_bar,w;

    not(w,Q_bar);
    not(Q_bar,Q);
    cmos(Q,in,clk,clk_bar);
    cmos(Q,w,clk_bar,clk);
endmodule;

verilog/modules/d_flip_flop.v
`include "../modules/d_latch.v"

module d_flip_flop(
    input in,
    input clk,
    input clk_bar,
    output Q,
    output Q_bar);

    wire w1, w2, w3, w4;

    not(w1,in);
    d_latch d1(w1,clk_bar,clk,,w2);
    d_latch d2(w2,clk,clk_bar,w4,w3);
    not(Q,w3);
    buf(Q_bar,w4);
endmodule;

verilog/modules/mux.v
module mux (A,B,S,Y);
    input A, B, S;
    output Y;
    wire Sbar;

    cmos(Y, A, S, ~S);
    cmos(Y, B, ~S, S);
endmodule;

verilog/modules/register.v
`include "../modules/mux.v"
`include "../modules/d_flip_flop.v"

module register(
    input in,
    input EN,
    input RST_bar,
    input CLK,
    input CLK_bar,
    output Q,
    output Q_bar);

    wire w1,w2;

    mux m1(in,Q,EN,w1);
    and(w2,w1,RST_bar);
    d_flip_flop d1(w2,CLK,CLK_bar,Q,Q_bar);
endmodule;

verilog/modules/FSM.v
`include "../modules/register.v"
`include "../modules/full_adder.v"

module FSM(
    input EN_in,
    input CLK_in,
    input RST_in,
    output EN,
    output CLK,
    output CLK_bar,
    output RST_bar);

    wire [1:0] counter; //For the adder
    wire [1:0] state;
    wire run;

    assign CLK = CLK_in;
    assign CLK_bar = ~CLK_in;
    assign RST_bar = ~RST_in;
    register r1(counter[0],EN_in,RST_bar,CLK,CLK_bar,state[0],);
    register r2(counter[1],EN_in,RST_bar,CLK,CLK_bar,state[1],);
    not(counter[0],state[0]);
    xor(counter[1],state[1],state[0]);
    nand(run,state[0],state[1]);
    and(EN,EN_in,run);
endmodule;

verilog/tests/FSM_tb.v
`include "../modules/FSM.v"

module FSM_tb;
    reg EN = 0;
    reg clk = 0;
    reg RST = 0;

    wire EN_out;
    always #1 clk = ~clk;

    FSM f1(EN,clk,RST,EN_out,,,);

    initial begin
        $dumpfile("../simulations/FSM_sim.vcd");
        $dumpvars(1, FSM_tb);
        RST=1;
        #1;
        RST=0;
        #20;
        EN = 1;
        #20;
        wait(~EN_out);
        wait(~clk);
        wait(clk); //1
        wait(~clk);
        wait(clk); //2
        EN = 0;
        #20;
        EN = 1;
        wait(~clk);
        wait(clk); //3
        wait(~clk);
        wait(clk); // pause
        #10;
        wait(~EN_out);
        wait(~clk);
        wait(clk); //1
        wait(~clk);
        wait(clk); //2
        RST = 1;
        #10;
        RST = 0;
        #20;
        //Starts from 1
        $finish();
    end;
endmodule;

verilog/simulations/FSM_sim.vcd
$date
	Tue Oct 24 17:52:15 2023
$end
$version
	Icarus Verilog
$end
$timescale
	1s
$end
$scope module FSM_tb $end
$var wire 1 ! EN_out $end
$var reg 1 " EN $end
$var reg 1 # RST $end
$var reg 1 $ clk $end
$upscope $end
$enddefinitions $end
$comment Show the parameter values. $end
$dumpall
$end
#0
$dumpvars
0$
1#
0"
0!
$end
#1
0#
1$
#2
0$
#3
1$
#4
0$
#5
1$
#6
0$
#7
1$
#8
0$
#9
1$
#10
0$
#11
1$
#12
0$
#13
1$
#14
0$
#15
1$
#16
0$
#17
1$
#18
0$
#19
1$
#20
0$
#21
1!
1$
1"
#22
0$
#23
1$
#24
0$
#25
1$
#26
0$
#27
0!
1$
#28
0$
#29
1!
1$
#30
0$
#31
1$
#32
0$
#33
1$
#34
0$
#35
0!
1$
#36
0$
#37
1!
1$
#38
0$
#39
1$
#40
0$
#41
1$
#42
0$
#43
0!
1$
#44
0$
#45
1!
1$
#46
0$
#47
0!
0"
1$
#48
0$
#49
1$
#50
0$
#51
1$
#52
0$
#53
1$
#54
0$
#55
1$
#56
0$
#57
1$
#58
0$
#59
1$
#60
0$
#61
1$
#62
0$
#63
1$
#64
0$
#65
1$
#66
0$
#67
1!
1$
1"
#68
0$
#69
1$
#70
0$
#71
0!
1$
#72
0$
#73
1!
1$
#74
0$
#75
1$
#76
0$
#77
1$
#78
0$
#79
0!
1$
#80
0$
#81
1!
1$
#82
0$
#83
1#
1$
#84
0$
#85
1$
#86
0$
#87
1$
#88
0$
#89
1$
#90
0$
#91
1$
#92
0$
#93
1$
0#
#94
0$
#95
1$
#96
0$
#97
1$
#98
0$
#99
0!
1$
#100
0$
#101
1!
1$
#102
0$
#103
1$
#104
0$
#105
1$
#106
0$
#107
0!
1$
#108
0$
#109
1!
1$
