verilog/modules/half_adder.v
`ifndef half_adder
`define half_adder
module half_adder(A,B,S,C);
    input A,B;
    output S,C;

    // S = A xor B
    cmos(S, A, ~B, B);
    cmos(S, ~A, B, ~B);

    and(C, A, B);
endmodule;


`endif

verilog/modules/full_adder.v
`include "../modules/half_adder.v"

module full_adder (A, B, C_in, S, C_out);
    input A,B,C_in;
    output S,C_out;
    wire s1,c1,c2;

    half_adder ha1(A,B,s1,c1);
    half_adder ha2(C_in,s1,S,c2);
    or(C_out,c1,c2);
endmodule;

verilog/tests/full_adder_tb.v
`include "../modules/full_adder.v"

module full_adder_tb;
    reg a,b,cin;
    wire s,cout;

    full_adder fa1(a,b,cin,s,cout);

    initial begin
        $dumpfile("../simulations/full_adder_sim.vcd");
        $dumpvars;

        a = 0; b = 0; cin = 0; #1;
        a = 0; b = 0; cin = 1; #1;
        a = 0; b = 1; cin = 0; #1;
        a = 0; b = 1; cin = 1; #1;
        a = 1; b = 0; cin = 0; #1;
        a = 1; b = 0; cin = 1; #1;
        a = 1; b = 1; cin = 0; #1;
        a = 1; b = 1; cin = 1; #1;
    end;
endmodule;

verilog/simulations/full_adder_sim.vcd
$date
	Mon Oct 23 16:58:37 2023
$end
$version
	Icarus Verilog
$end
$timescale
	1s
$end
$scope module full_adder_tb $end
$var wire 1 ! s $end
$var wire 1 " cout $end
$var reg 1 # a $end
$var reg 1 $ b $end
$var reg 1 % cin $end
$scope module fa1 $end
$var wire 1 # A $end
$var wire 1 $ B $end
$var wire 1 % C_in $end
$var wire 1 " C_out $end
$var wire 1 ! S $end
$var wire 1 & s1 $end
$var wire 1 ' c2 $end
$var wire 1 ( c1 $end
$scope module ha1 $end
$var wire 1 # A $end
$var wire 1 $ B $end
$var wire 1 ( C $end
$var wire 1 & S $end
$upscope $end
$scope module ha2 $end
$var wire 1 % A $end
$var wire 1 & B $end
$var wire 1 ' C $end
$var wire 1 ! S $end
$upscope $end
$upscope $end
$upscope $end
$enddefinitions $end
$comment Show the parameter values. $end
$dumpall
$end
#0
$dumpvars
0(
0'
0&
0%
0$
0#
0"
0!
$end
#1
1!
1%
#2
0%
1!
1&
1$
#3
1"
0!
1'
1%
#4
0"
1!
0'
1&
0%
0$
1#
#5
1"
0!
1'
1%
#6
0'
1(
0%
0!
0&
1$
#7
1!
1%
