verilog/modules/d_latch.v
module d_latch(
    input in,
    input clk,
    input clk_bar,
    output Q,
    output Q_bar);

    wire clk_bar,w;

    not(w,Q_bar);
    not(Q_bar,Q);
    cmos(Q,in,clk,clk_bar);
    cmos(Q,w,clk_bar,clk);
endmodule;

verilog/modules/d_flip_flop.v
`include "../modules/d_latch.v"

module d_flip_flop(
    input in,
    input clk,
    input clk_bar,
    output Q,
    output Q_bar);

    wire w1, w2, w3, w4;

    not(w1,in);
    d_latch d1(w1,clk_bar,clk,,w2);
    d_latch d2(w2,clk,clk_bar,w4,w3);
    not(Q,w3);
    buf(Q_bar,w4);
endmodule;

verilog/modules/mux.v
module mux (A,B,S,Y);
    input A, B, S;
    output Y;
    wire Sbar;

    cmos(Y, A, S, ~S);
    cmos(Y, B, ~S, S);
endmodule;

verilog/modules/register.v
`include "../modules/mux.v"
`include "../modules/d_flip_flop.v"

module register(
    input in,
    input EN,
    input RST_bar,
    input CLK,
    input CLK_bar,
    output Q,
    output Q_bar);

    wire w1,w2;

    mux m1(in,Q,EN,w1);
    and(w2,w1,RST_bar);
    d_flip_flop d1(w2,CLK,CLK_bar,Q,Q_bar);
endmodule;

verilog/modules/register_8_bit.v
`include "../modules/register.v"

module register_8_bit(
    input [7:0] In,
    input EN,
    input RST_bar,
    input CLK,
    input CLK_bar,
    output [7:0] Q,
    output [7:0] Q_bar);

    register r0(In[0],EN,RST_bar,CLK,CLK_bar,Q[0],Q_bar[0]);
    register r1(In[1],EN,RST_bar,CLK,CLK_bar,Q[1],Q_bar[1]);
    register r2(In[2],EN,RST_bar,CLK,CLK_bar,Q[2],Q_bar[2]);
    register r3(In[3],EN,RST_bar,CLK,CLK_bar,Q[3],Q_bar[3]);
    register r4(In[4],EN,RST_bar,CLK,CLK_bar,Q[4],Q_bar[4]);
    register r5(In[5],EN,RST_bar,CLK,CLK_bar,Q[5],Q_bar[5]);
    register r6(In[6],EN,RST_bar,CLK,CLK_bar,Q[6],Q_bar[6]);
    register r7(In[7],EN,RST_bar,CLK,CLK_bar,Q[7],Q_bar[7]);
endmodule;

verilog/modules/half_adder.v
module half_adder(A,B,S,C);
    input A,B;
    output S,C;

    // S = A xor B
    cmos(S, A, ~B, B);
    cmos(S, ~A, B, ~B);

    and(C, A, B);
endmodule;

verilog/modules/full_adder.v
`include "../modules/half_adder.v"

module full_adder (A, B, C_in, S, C_out);
    input A,B,C_in;
    output S,C_out;
    wire s1,c1,c2;

    half_adder ha1(A,B,s1,c1);
    half_adder ha2(C_in,s1,S,c2);
    or(C_out,c1,c2);
endmodule;

verilog/modules/adder_8_bit.v
`include "../modules/full_adder.v"

module adder_8_bit(
    input [7:0] a,
    input [7:0] b,
    output [7:0] s,
    output c );

    wire [6:0] c_sub;

    half_adder ha1(a[0],b[0],s[0],c_sub[0]);
    full_adder fa1(a[1],b[1],c_sub[0],s[1],c_sub[1]);
    full_adder fa2(a[2],b[2],c_sub[1],s[2],c_sub[2]);
    full_adder fa3(a[3],b[3],c_sub[2],s[3],c_sub[3]);
    full_adder fa4(a[4],b[4],c_sub[3],s[4],c_sub[4]);
    full_adder fa5(a[5],b[5],c_sub[4],s[5],c_sub[5]);
    full_adder fa6(a[6],b[6],c_sub[5],s[6],c_sub[6]);
    full_adder fa7(a[7],b[7],c_sub[6],s[7],c);
endmodule;

verilog/modules/mul.v
`include "../modules/half_adder.v"

module mul(
    input [1:0] A,
    input [1:0] B,
    output [3:0] C);

    wire w1,w2,w3,w4;

    and(C[0],A[0],B[0]);
    and(w1,A[0],B[1]);
    and(w2,A[1],B[0]);
    and(w3,A[1],B[1]);

    half_adder ha1(w1,w2,C[1],w4);
    half_adder ha2(w3,w4,C[2],C[3]);
endmodule;

verilog/modules/mac.v
`include "../modules/mul.v"
`include "../modules/adder_8_bit.v"
`include "../modules/register_8_bit.v"

`ifndef mac
`define mac

module mac(
    input [1:0] A,
    input [1:0] B,
    input EN,
    input RST_bar,
    input CLK,
    input CLK_bar,
    output [7:0] Q);

    wire [3:0] M;
    wire [3:0] padding = 0;
    wire [7:0] S;

    mul m1(A,B,M);
    adder_8_bit a1({padding,M},Q,S,);
    register_8_bit r1(S,EN,RST_bar,CLK,CLK_bar,Q,);
endmodule;

`endif

verilog/tests/mac_tb.v
`include "../modules/mac.v"

module mac_tb;
    reg [1:0] A = 0;
    reg [1:0] B = 0;
    
    wire [7:0] Q;

    reg EN = 0;

    reg RST = 0;
    wire RST_bar;
    assign RST_bar = ~RST;

    reg clk = 0;
    wire clk_bar;
    assign clk_bar = ~clk;
    always #1 clk = ~clk;

    mac M1(A,B,EN,RST_bar,clk,clk_bar,Q);

    initial begin
        $dumpfile("../simulations/mac_sim.vcd");
        $dumpvars(0,mac_tb);
        RST = 1;
        #1;
        RST = 0;
        A = 1;
        EN = 1;
        #10;
        EN = 0;
        B = 1;
        #10;
        EN = 1;
        #20;
        RST = 1;
        #10;
        A = 2;
        RST = 0;
        #10;
        A = 3;
        RST = 1;
        #3;
        RST = 0;
        #10
        $finish();
    end
endmodule;

verilog/simulations/mac_sim.vcd
$date
	Tue Oct 24 16:27:39 2023
$end
$version
	Icarus Verilog
$end
$timescale
	1s
$end
$scope module mac_tb $end
$var wire 1 ! RST_bar $end
$var wire 1 " clk_bar $end
$var wire 8 # Q [7:0] $end
$var reg 2 $ A [1:0] $end
$var reg 2 % B [1:0] $end
$var reg 1 & EN $end
$var reg 1 ' RST $end
$var reg 1 ( clk $end
$scope module M1 $end
$var wire 2 ) A [1:0] $end
$var wire 2 * B [1:0] $end
$var wire 1 ( CLK $end
$var wire 1 " CLK_bar $end
$var wire 1 & EN $end
$var wire 1 ! RST_bar $end
$var wire 4 + padding [3:0] $end
$var wire 8 , S [7:0] $end
$var wire 8 - Q [7:0] $end
$var wire 4 . M [3:0] $end
$scope module a1 $end
$var wire 8 / a [7:0] $end
$var wire 8 0 s [7:0] $end
$var wire 7 1 c_sub [6:0] $end
$var wire 1 2 c $end
$var wire 8 3 b [7:0] $end
$scope module fa1 $end
$var wire 1 4 A $end
$var wire 1 5 B $end
$var wire 1 6 C_in $end
$var wire 1 7 C_out $end
$var wire 1 8 S $end
$var wire 1 9 s1 $end
$var wire 1 : c2 $end
$var wire 1 ; c1 $end
$scope module ha1 $end
$var wire 1 4 A $end
$var wire 1 5 B $end
$var wire 1 ; C $end
$var wire 1 9 S $end
$upscope $end
$scope module ha2 $end
$var wire 1 6 A $end
$var wire 1 9 B $end
$var wire 1 : C $end
$var wire 1 8 S $end
$upscope $end
$upscope $end
$scope module fa2 $end
$var wire 1 < A $end
$var wire 1 = B $end
$var wire 1 > C_in $end
$var wire 1 ? C_out $end
$var wire 1 @ S $end
$var wire 1 A s1 $end
$var wire 1 B c2 $end
$var wire 1 C c1 $end
$scope module ha1 $end
$var wire 1 < A $end
$var wire 1 = B $end
$var wire 1 C C $end
$var wire 1 A S $end
$upscope $end
$scope module ha2 $end
$var wire 1 > A $end
$var wire 1 A B $end
$var wire 1 B C $end
$var wire 1 @ S $end
$upscope $end
$upscope $end
$scope module fa3 $end
$var wire 1 D A $end
$var wire 1 E B $end
$var wire 1 F C_in $end
$var wire 1 G C_out $end
$var wire 1 H S $end
$var wire 1 I s1 $end
$var wire 1 J c2 $end
$var wire 1 K c1 $end
$scope module ha1 $end
$var wire 1 D A $end
$var wire 1 E B $end
$var wire 1 K C $end
$var wire 1 I S $end
$upscope $end
$scope module ha2 $end
$var wire 1 F A $end
$var wire 1 I B $end
$var wire 1 J C $end
$var wire 1 H S $end
$upscope $end
$upscope $end
$scope module fa4 $end
$var wire 1 L A $end
$var wire 1 M B $end
$var wire 1 N C_in $end
$var wire 1 O C_out $end
$var wire 1 P S $end
$var wire 1 Q s1 $end
$var wire 1 R c2 $end
$var wire 1 S c1 $end
$scope module ha1 $end
$var wire 1 L A $end
$var wire 1 M B $end
$var wire 1 S C $end
$var wire 1 Q S $end
$upscope $end
$scope module ha2 $end
$var wire 1 N A $end
$var wire 1 Q B $end
$var wire 1 R C $end
$var wire 1 P S $end
$upscope $end
$upscope $end
$scope module fa5 $end
$var wire 1 T A $end
$var wire 1 U B $end
$var wire 1 V C_in $end
$var wire 1 W C_out $end
$var wire 1 X S $end
$var wire 1 Y s1 $end
$var wire 1 Z c2 $end
$var wire 1 [ c1 $end
$scope module ha1 $end
$var wire 1 T A $end
$var wire 1 U B $end
$var wire 1 [ C $end
$var wire 1 Y S $end
$upscope $end
$scope module ha2 $end
$var wire 1 V A $end
$var wire 1 Y B $end
$var wire 1 Z C $end
$var wire 1 X S $end
$upscope $end
$upscope $end
$scope module fa6 $end
$var wire 1 \ A $end
$var wire 1 ] B $end
$var wire 1 ^ C_in $end
$var wire 1 _ C_out $end
$var wire 1 ` S $end
$var wire 1 a s1 $end
$var wire 1 b c2 $end
$var wire 1 c c1 $end
$scope module ha1 $end
$var wire 1 \ A $end
$var wire 1 ] B $end
$var wire 1 c C $end
$var wire 1 a S $end
$upscope $end
$scope module ha2 $end
$var wire 1 ^ A $end
$var wire 1 a B $end
$var wire 1 b C $end
$var wire 1 ` S $end
$upscope $end
$upscope $end
$scope module fa7 $end
$var wire 1 d A $end
$var wire 1 e B $end
$var wire 1 f C_in $end
$var wire 1 2 C_out $end
$var wire 1 g S $end
$var wire 1 h s1 $end
$var wire 1 i c2 $end
$var wire 1 j c1 $end
$scope module ha1 $end
$var wire 1 d A $end
$var wire 1 e B $end
$var wire 1 j C $end
$var wire 1 h S $end
$upscope $end
$scope module ha2 $end
$var wire 1 f A $end
$var wire 1 h B $end
$var wire 1 i C $end
$var wire 1 g S $end
$upscope $end
$upscope $end
$scope module ha1 $end
$var wire 1 k A $end
$var wire 1 l B $end
$var wire 1 m C $end
$var wire 1 n S $end
$upscope $end
$upscope $end
$scope module m1 $end
$var wire 2 o A [1:0] $end
$var wire 2 p B [1:0] $end
$var wire 1 q w1 $end
$var wire 1 r w2 $end
$var wire 1 s w3 $end
$var wire 1 t w4 $end
$var wire 4 u C [3:0] $end
$scope module ha1 $end
$var wire 1 q A $end
$var wire 1 r B $end
$var wire 1 t C $end
$var wire 1 v S $end
$upscope $end
$scope module ha2 $end
$var wire 1 s A $end
$var wire 1 t B $end
$var wire 1 w C $end
$var wire 1 x S $end
$upscope $end
$upscope $end
$scope module r1 $end
$var wire 1 ( CLK $end
$var wire 1 " CLK_bar $end
$var wire 1 & EN $end
$var wire 8 y In [7:0] $end
$var wire 1 ! RST_bar $end
$var wire 8 z Q_bar [7:0] $end
$var wire 8 { Q [7:0] $end
$scope module r0 $end
$var wire 1 ( CLK $end
$var wire 1 " CLK_bar $end
$var wire 1 & EN $end
$var wire 1 ! RST_bar $end
$var wire 1 | in $end
$var wire 1 } w1 $end
$var wire 1 ~ w2 $end
$var wire 1 !" Q_bar $end
$var wire 1 "" Q $end
$scope module d1 $end
$var wire 1 "" Q $end
$var wire 1 !" Q_bar $end
$var wire 1 ( clk $end
$var wire 1 " clk_bar $end
$var wire 1 ~ in $end
$var wire 1 #" w1 $end
$var wire 1 $" w4 $end
$var wire 1 %" w3 $end
$var wire 1 &" w2 $end
$scope module d1 $end
$var wire 1 '" Q $end
$var wire 1 &" Q_bar $end
$var wire 1 " clk $end
$var wire 1 ( clk_bar $end
$var wire 1 #" in $end
$var wire 1 (" w $end
$upscope $end
$scope module d2 $end
$var wire 1 $" Q $end
$var wire 1 %" Q_bar $end
$var wire 1 ( clk $end
$var wire 1 " clk_bar $end
$var wire 1 &" in $end
$var wire 1 )" w $end
$upscope $end
$upscope $end
$scope module m1 $end
$var wire 1 | A $end
$var wire 1 "" B $end
$var wire 1 & S $end
$var wire 1 } Y $end
$upscope $end
$upscope $end
$scope module r1 $end
$var wire 1 ( CLK $end
$var wire 1 " CLK_bar $end
$var wire 1 & EN $end
$var wire 1 ! RST_bar $end
$var wire 1 *" in $end
$var wire 1 +" w1 $end
$var wire 1 ," w2 $end
$var wire 1 -" Q_bar $end
$var wire 1 ." Q $end
$scope module d1 $end
$var wire 1 ." Q $end
$var wire 1 -" Q_bar $end
$var wire 1 ( clk $end
$var wire 1 " clk_bar $end
$var wire 1 ," in $end
$var wire 1 /" w1 $end
$var wire 1 0" w4 $end
$var wire 1 1" w3 $end
$var wire 1 2" w2 $end
$scope module d1 $end
$var wire 1 3" Q $end
$var wire 1 2" Q_bar $end
$var wire 1 " clk $end
$var wire 1 ( clk_bar $end
$var wire 1 /" in $end
$var wire 1 4" w $end
$upscope $end
$scope module d2 $end
$var wire 1 0" Q $end
$var wire 1 1" Q_bar $end
$var wire 1 ( clk $end
$var wire 1 " clk_bar $end
$var wire 1 2" in $end
$var wire 1 5" w $end
$upscope $end
$upscope $end
$scope module m1 $end
$var wire 1 *" A $end
$var wire 1 ." B $end
$var wire 1 & S $end
$var wire 1 +" Y $end
$upscope $end
$upscope $end
$scope module r2 $end
$var wire 1 ( CLK $end
$var wire 1 " CLK_bar $end
$var wire 1 & EN $end
$var wire 1 ! RST_bar $end
$var wire 1 6" in $end
$var wire 1 7" w1 $end
$var wire 1 8" w2 $end
$var wire 1 9" Q_bar $end
$var wire 1 :" Q $end
$scope module d1 $end
$var wire 1 :" Q $end
$var wire 1 9" Q_bar $end
$var wire 1 ( clk $end
$var wire 1 " clk_bar $end
$var wire 1 8" in $end
$var wire 1 ;" w1 $end
$var wire 1 <" w4 $end
$var wire 1 =" w3 $end
$var wire 1 >" w2 $end
$scope module d1 $end
$var wire 1 ?" Q $end
$var wire 1 >" Q_bar $end
$var wire 1 " clk $end
$var wire 1 ( clk_bar $end
$var wire 1 ;" in $end
$var wire 1 @" w $end
$upscope $end
$scope module d2 $end
$var wire 1 <" Q $end
$var wire 1 =" Q_bar $end
$var wire 1 ( clk $end
$var wire 1 " clk_bar $end
$var wire 1 >" in $end
$var wire 1 A" w $end
$upscope $end
$upscope $end
$scope module m1 $end
$var wire 1 6" A $end
$var wire 1 :" B $end
$var wire 1 & S $end
$var wire 1 7" Y $end
$upscope $end
$upscope $end
$scope module r3 $end
$var wire 1 ( CLK $end
$var wire 1 " CLK_bar $end
$var wire 1 & EN $end
$var wire 1 ! RST_bar $end
$var wire 1 B" in $end
$var wire 1 C" w1 $end
$var wire 1 D" w2 $end
$var wire 1 E" Q_bar $end
$var wire 1 F" Q $end
$scope module d1 $end
$var wire 1 F" Q $end
$var wire 1 E" Q_bar $end
$var wire 1 ( clk $end
$var wire 1 " clk_bar $end
$var wire 1 D" in $end
$var wire 1 G" w1 $end
$var wire 1 H" w4 $end
$var wire 1 I" w3 $end
$var wire 1 J" w2 $end
$scope module d1 $end
$var wire 1 K" Q $end
$var wire 1 J" Q_bar $end
$var wire 1 " clk $end
$var wire 1 ( clk_bar $end
$var wire 1 G" in $end
$var wire 1 L" w $end
$upscope $end
$scope module d2 $end
$var wire 1 H" Q $end
$var wire 1 I" Q_bar $end
$var wire 1 ( clk $end
$var wire 1 " clk_bar $end
$var wire 1 J" in $end
$var wire 1 M" w $end
$upscope $end
$upscope $end
$scope module m1 $end
$var wire 1 B" A $end
$var wire 1 F" B $end
$var wire 1 & S $end
$var wire 1 C" Y $end
$upscope $end
$upscope $end
$scope module r4 $end
$var wire 1 ( CLK $end
$var wire 1 " CLK_bar $end
$var wire 1 & EN $end
$var wire 1 ! RST_bar $end
$var wire 1 N" in $end
$var wire 1 O" w1 $end
$var wire 1 P" w2 $end
$var wire 1 Q" Q_bar $end
$var wire 1 R" Q $end
$scope module d1 $end
$var wire 1 R" Q $end
$var wire 1 Q" Q_bar $end
$var wire 1 ( clk $end
$var wire 1 " clk_bar $end
$var wire 1 P" in $end
$var wire 1 S" w1 $end
$var wire 1 T" w4 $end
$var wire 1 U" w3 $end
$var wire 1 V" w2 $end
$scope module d1 $end
$var wire 1 W" Q $end
$var wire 1 V" Q_bar $end
$var wire 1 " clk $end
$var wire 1 ( clk_bar $end
$var wire 1 S" in $end
$var wire 1 X" w $end
$upscope $end
$scope module d2 $end
$var wire 1 T" Q $end
$var wire 1 U" Q_bar $end
$var wire 1 ( clk $end
$var wire 1 " clk_bar $end
$var wire 1 V" in $end
$var wire 1 Y" w $end
$upscope $end
$upscope $end
$scope module m1 $end
$var wire 1 N" A $end
$var wire 1 R" B $end
$var wire 1 & S $end
$var wire 1 O" Y $end
$upscope $end
$upscope $end
$scope module r5 $end
$var wire 1 ( CLK $end
$var wire 1 " CLK_bar $end
$var wire 1 & EN $end
$var wire 1 ! RST_bar $end
$var wire 1 Z" in $end
$var wire 1 [" w1 $end
$var wire 1 \" w2 $end
$var wire 1 ]" Q_bar $end
$var wire 1 ^" Q $end
$scope module d1 $end
$var wire 1 ^" Q $end
$var wire 1 ]" Q_bar $end
$var wire 1 ( clk $end
$var wire 1 " clk_bar $end
$var wire 1 \" in $end
$var wire 1 _" w1 $end
$var wire 1 `" w4 $end
$var wire 1 a" w3 $end
$var wire 1 b" w2 $end
$scope module d1 $end
$var wire 1 c" Q $end
$var wire 1 b" Q_bar $end
$var wire 1 " clk $end
$var wire 1 ( clk_bar $end
$var wire 1 _" in $end
$var wire 1 d" w $end
$upscope $end
$scope module d2 $end
$var wire 1 `" Q $end
$var wire 1 a" Q_bar $end
$var wire 1 ( clk $end
$var wire 1 " clk_bar $end
$var wire 1 b" in $end
$var wire 1 e" w $end
$upscope $end
$upscope $end
$scope module m1 $end
$var wire 1 Z" A $end
$var wire 1 ^" B $end
$var wire 1 & S $end
$var wire 1 [" Y $end
$upscope $end
$upscope $end
$scope module r6 $end
$var wire 1 ( CLK $end
$var wire 1 " CLK_bar $end
$var wire 1 & EN $end
$var wire 1 ! RST_bar $end
$var wire 1 f" in $end
$var wire 1 g" w1 $end
$var wire 1 h" w2 $end
$var wire 1 i" Q_bar $end
$var wire 1 j" Q $end
$scope module d1 $end
$var wire 1 j" Q $end
$var wire 1 i" Q_bar $end
$var wire 1 ( clk $end
$var wire 1 " clk_bar $end
$var wire 1 h" in $end
$var wire 1 k" w1 $end
$var wire 1 l" w4 $end
$var wire 1 m" w3 $end
$var wire 1 n" w2 $end
$scope module d1 $end
$var wire 1 o" Q $end
$var wire 1 n" Q_bar $end
$var wire 1 " clk $end
$var wire 1 ( clk_bar $end
$var wire 1 k" in $end
$var wire 1 p" w $end
$upscope $end
$scope module d2 $end
$var wire 1 l" Q $end
$var wire 1 m" Q_bar $end
$var wire 1 ( clk $end
$var wire 1 " clk_bar $end
$var wire 1 n" in $end
$var wire 1 q" w $end
$upscope $end
$upscope $end
$scope module m1 $end
$var wire 1 f" A $end
$var wire 1 j" B $end
$var wire 1 & S $end
$var wire 1 g" Y $end
$upscope $end
$upscope $end
$scope module r7 $end
$var wire 1 ( CLK $end
$var wire 1 " CLK_bar $end
$var wire 1 & EN $end
$var wire 1 ! RST_bar $end
$var wire 1 r" in $end
$var wire 1 s" w1 $end
$var wire 1 t" w2 $end
$var wire 1 u" Q_bar $end
$var wire 1 v" Q $end
$scope module d1 $end
$var wire 1 v" Q $end
$var wire 1 u" Q_bar $end
$var wire 1 ( clk $end
$var wire 1 " clk_bar $end
$var wire 1 t" in $end
$var wire 1 w" w1 $end
$var wire 1 x" w4 $end
$var wire 1 y" w3 $end
$var wire 1 z" w2 $end
$scope module d1 $end
$var wire 1 {" Q $end
$var wire 1 z" Q_bar $end
$var wire 1 " clk $end
$var wire 1 ( clk_bar $end
$var wire 1 w" in $end
$var wire 1 |" w $end
$upscope $end
$scope module d2 $end
$var wire 1 x" Q $end
$var wire 1 y" Q_bar $end
$var wire 1 ( clk $end
$var wire 1 " clk_bar $end
$var wire 1 z" in $end
$var wire 1 }" w $end
$upscope $end
$upscope $end
$scope module m1 $end
$var wire 1 r" A $end
$var wire 1 v" B $end
$var wire 1 & S $end
$var wire 1 s" Y $end
$upscope $end
$upscope $end
$upscope $end
$upscope $end
$upscope $end
$enddefinitions $end
$comment Show the parameter values. $end
$dumpall
$end
#0
$dumpvars
x}"
1|"
1{"
0z"
xy"
xx"
1w"
xv"
xu"
0t"
xs"
xr"
xq"
1p"
1o"
0n"
xm"
xl"
1k"
xj"
xi"
0h"
xg"
xf"
xe"
1d"
1c"
0b"
xa"
x`"
1_"
x^"
x]"
0\"
x["
xZ"
xY"
1X"
1W"
0V"
xU"
xT"
1S"
xR"
xQ"
0P"
xO"
xN"
xM"
1L"
1K"
0J"
xI"
xH"
1G"
xF"
xE"
0D"
xC"
xB"
xA"
1@"
1?"
0>"
x="
x<"
1;"
x:"
x9"
08"
x7"
x6"
x5"
14"
13"
02"
x1"
x0"
1/"
x."
x-"
0,"
x+"
x*"
x)"
1("
1'"
0&"
x%"
x$"
1#"
x""
x!"
0~
x}
x|
bx {
bx z
bx y
0x
0w
0v
b0 u
0t
0s
0r
0q
b0 p
b0 o
xn
0m
xl
0k
0j
0i
xh
xg
0f
xe
0d
0c
0b
xa
x`
0_
0^
x]
0\
0[
0Z
xY
xX
0W
0V
xU
0T
0S
0R
xQ
xP
0O
0N
xM
0L
0K
0J
xI
xH
0G
0F
xE
0D
0C
0B
xA
x@
0?
0>
x=
0<
0;
0:
x9
x8
07
06
x5
04
bx 3
02
b0 1
bx 0
b0 /
b0 .
bx -
bx ,
b0 +
b0 *
b0 )
0(
1'
0&
b0 %
b0 $
bx #
1"
0!
$end
#1
0+"
0*"
07"
06"
0C"
0B"
0O"
0N"
0["
0Z"
0g"
0f"
0s"
0r"
0}
0|
08
0@
0H
0P
0X
0`
0g
b0 ,
b0 0
b0 y
0n
09
0A
0I
0Q
0Y
0a
0h
0l
05
0=
0E
0M
0U
0]
0e
1#"
1/"
1;"
1G"
1S"
1_"
1k"
1w"
0)"
0""
05"
0."
0A"
0:"
0M"
0F"
0Y"
0R"
0e"
0^"
0q"
0j"
0}"
b0 #
b0 -
b0 3
b0 {
0v"
0~
0,"
08"
0D"
0P"
0\"
0h"
0t"
0!"
1%"
0-"
11"
09"
1="
0E"
1I"
0Q"
1U"
0]"
1a"
0i"
1m"
b0 z
0u"
1y"
1!
0$"
00"
0<"
0H"
0T"
0`"
0l"
0x"
0"
1&
b1 $
b1 )
b1 o
0'
1(
#2
1"
0(
#3
0"
1(
#4
1"
0(
#5
0"
1(
#6
1"
0(
#7
0"
1(
#8
1"
0(
#9
0"
1(
#10
1"
0(
#11
1|
b1 ,
b1 0
b1 y
1n
1k
b1 /
b1 .
b1 u
0"
1(
b1 %
b1 *
b1 p
0&
#12
1"
0(
#13
0"
1(
#14
1"
0(
#15
0"
1(
#16
1"
0(
#17
0"
1(
#18
1"
0(
#19
0"
1(
#20
1"
0(
#21
0#"
0"
1~
1(
1}
1&
#22
0("
1&"
1"
0'"
0(
#23
0/"
1,"
1#"
1+"
1*"
0~
18
16
0}
0|
b1 1
1m
b10 ,
b10 0
b10 y
0n
1l
1)"
b1 #
b1 -
b1 3
b1 {
1""
b1 z
1!"
0%"
0"
1$"
1(
#24
1("
04"
0&"
12"
1"
1'"
03"
0(
#25
1;"
08"
07"
06"
0#"
0/"
0@
0>
1~
06
1,"
07
1}
1|
b0 1
0m
1+"
1*"
0:
1n
0l
b11 ,
b11 0
b11 y
18
19
15
0)"
0""
15"
b10 #
b10 -
b10 3
b10 {
1."
0!"
1%"
b10 z
1-"
01"
0"
0$"
10"
1(
#26
0("
1&"
1"
0'"
0(
#27
0;"
18"
1/"
17"
16"
0,"
1@
1>
0+"
0*"
17
1#"
08
1:
0~
16
0}
0|
b11 1
1m
b100 ,
b100 0
b100 y
0n
1l
1)"
b11 #
b11 -
b11 3
b11 {
1""
b11 z
1!"
0%"
0"
1$"
1(
#28
1("
14"
0@"
0&"
02"
1>"
1"
1'"
13"
0?"
0(
#29
1G"
0D"
0C"
0B"
0#"
1/"
0>
0;"
0H
0F
1~
06
0,"
07
18"
0?
1}
1|
b0 1
0m
0+"
0*"
0:
17"
16"
0B
1n
0l
08
09
05
b101 ,
b101 0
b101 y
1@
1A
1=
0)"
0""
05"
0."
1A"
b100 #
b100 -
b100 3
b100 {
1:"
0!"
1%"
0-"
11"
b100 z
19"
0="
0"
0$"
00"
1<"
1(
#30
0("
1&"
1"
0'"
0(
#31
0/"
1,"
1#"
1+"
1*"
0~
18
16
0}
0|
b1 1
1m
b110 ,
b110 0
b110 y
0n
1l
1)"
b101 #
b101 -
b101 3
b101 {
1""
b101 z
1!"
0%"
0"
1$"
1(
#32
1("
04"
0&"
12"
1"
1'"
03"
0(
#33
1G"
0D"
0;"
0C"
0B"
18"
0H
0F
17"
16"
0?
1@
0B
0#"
0/"
0>
1~
06
1,"
07
1}
1|
b0 1
0m
1+"
1*"
0:
1n
0l
b111 ,
b111 0
b111 y
18
19
15
0)"
0""
15"
b110 #
b110 -
b110 3
b110 {
1."
0!"
1%"
b110 z
1-"
01"
0"
0$"
10"
1(
#34
0("
1&"
1"
0'"
0(
#35
0G"
1D"
1;"
1C"
1B"
08"
1H
1F
07"
06"
1?
1/"
0@
1B
0,"
1>
0+"
0*"
17
1#"
08
1:
0~
16
0}
0|
b111 1
1m
b1000 ,
b1000 0
b1000 y
0n
1l
1)"
b111 #
b111 -
b111 3
b111 {
1""
b111 z
1!"
0%"
0"
1$"
1(
#36
1("
14"
1@"
0L"
0&"
02"
0>"
1J"
1"
1'"
13"
1?"
0K"
0(
#37
1S"
0P"
0O"
0N"
0#"
1/"
0>
1;"
0F
0G"
0P
0N
1~
06
0,"
07
08"
0?
1D"
0G
1}
1|
b0 1
0m
0+"
0*"
0:
07"
06"
0B
1C"
1B"
0J
1n
0l
08
09
05
0@
0A
0=
b1001 ,
b1001 0
b1001 y
1H
1I
1E
0)"
0""
05"
0."
0A"
0:"
1M"
b1000 #
b1000 -
b1000 3
b1000 {
1F"
0!"
1%"
0-"
11"
09"
1="
b1000 z
1E"
0I"
0"
0$"
00"
0<"
1H"
1(
#38
0("
1&"
1"
0'"
0(
#39
0/"
1,"
1#"
1+"
1*"
0~
18
16
0}
0|
b1 1
1m
b1010 ,
b1010 0
b1010 y
0n
1l
1)"
b1001 #
b1001 -
b1001 3
b1001 {
1""
b1001 z
1!"
0%"
0"
1$"
1(
#40
1("
04"
0&"
12"
1"
1'"
03"
0(
#41
07"
06"
0@
0>
06
07
1}
1|
b0 1
0m
1+"
1*"
0:
1n
0l
b1011 ,
b1011 0
b1011 y
18
19
15
1/"
1G"
0)"
0""
15"
b1010 #
b1010 -
b1010 3
b1010 {
1."
0,"
0D"
0!"
1%"
b1010 z
1-"
01"
0"
0!
0$"
10"
1(
1'
#42
14"
1L"
02"
0J"
1"
13"
1K"
0(
#43
0+"
0*"
0C"
0B"
08
09
05
b1 ,
b1 0
b1 y
0H
0I
0E
05"
0."
0M"
b0 #
b0 -
b0 3
b0 {
0F"
0-"
11"
b0 z
0E"
1I"
0"
00"
0H"
1(
#44
1"
0(
#45
0"
1(
#46
1"
0(
#47
0"
1(
#48
1"
0(
#49
0"
1(
#50
1"
0(
#51
0/"
1,"
0}
0|
1+"
1*"
1#"
0n
0k
b10 ,
b10 0
b10 y
18
19
14
0~
b10 /
b10 .
b10 u
1v
1r
0"
1!
1(
0'
b10 $
b10 )
b10 o
#52
04"
12"
1"
03"
0(
#53
0;"
18"
17"
16"
1/"
1@
1>
0,"
b10 1
17
0+"
0*"
1;
b100 ,
b100 0
b100 y
08
09
15
15"
b10 #
b10 -
b10 3
b10 {
1."
b10 z
1-"
01"
0"
10"
1(
#54
14"
0@"
02"
1>"
1"
13"
0?"
0(
#55
1G"
0D"
0C"
0B"
0/"
0>
0;"
0H
0F
1,"
07
18"
b0 1
0?
1+"
1*"
0;
17"
16"
0B
18
19
05
b110 ,
b110 0
b110 y
1@
1A
1=
05"
0."
1A"
b100 #
b100 -
b100 3
b100 {
1:"
0-"
11"
b100 z
19"
0="
0"
00"
1<"
1(
#56
04"
12"
1"
03"
0(
#57
0G"
1D"
1;"
1C"
1B"
08"
1H
1F
07"
06"
1?
0@
1B
1/"
1>
0,"
b110 1
17
0+"
0*"
1;
b1000 ,
b1000 0
b1000 y
08
09
15
15"
b110 #
b110 -
b110 3
b110 {
1."
b110 z
1-"
01"
0"
10"
1(
#58
14"
1@"
0L"
02"
0>"
1J"
1"
13"
1?"
0K"
0(
#59
1S"
0P"
0O"
0N"
0/"
0>
1;"
0F
0G"
0P
0N
1,"
07
08"
0?
1D"
b0 1
0G
1+"
1*"
0;
07"
06"
0B
1C"
1B"
0J
18
19
05
0@
0A
0=
b1010 ,
b1010 0
b1010 y
1H
1I
1E
05"
0."
0A"
0:"
1M"
b1000 #
b1000 -
b1000 3
b1000 {
1F"
0-"
11"
09"
1="
b1000 z
1E"
0I"
0"
00"
0<"
1H"
1(
#60
04"
12"
1"
03"
0(
#61
17"
16"
1@
1>
b10 1
17
0+"
0*"
1;
1}
1|
08
09
15
1/"
1G"
b1101 ,
b1101 0
b1101 y
1n
1k
15"
b1010 #
b1010 -
b1010 3
b1010 {
1."
0,"
0D"
b11 /
b11 .
b11 u
b1010 z
1-"
01"
0"
0!
10"
1(
1'
b11 $
b11 )
b11 o
#62
14"
1L"
02"
0J"
1"
13"
1K"
0(
#63
07"
06"
0@
0>
b0 1
07
1+"
1*"
0;
0C"
0B"
18
19
05
b11 ,
b11 0
b11 y
0H
0I
0E
05"
0."
0M"
b0 #
b0 -
b0 3
b0 {
0F"
0-"
11"
b0 z
0E"
1I"
0"
00"
0H"
1(
#64
0("
04"
1&"
12"
0'"
0#"
03"
0/"
1~
1,"
1"
1!
0(
0'
