verilog/modules/half_adder.v
module half_adder(A,B,S,C);
    input A,B;
    output S,C;

    // S = A xor B
    cmos(S, A, ~B, B);
    cmos(S, ~A, B, ~B);

    and(C, A, B);
endmodule;

verilog/modules/mul.v
`include "../modules/half_adder.v"

module mul(
    input [1:0] A,
    input [1:0] B,
    output [3:0] C);

    wire w1,w2,w3,w4;

    and(C[0],A[0],B[0]);
    and(w1,A[0],B[1]);
    and(w2,A[1],B[0]);
    and(w3,A[1],B[1]);

    half_adder ha1(w1,w2,C[1],w4);
    half_adder ha2(w3,w4,C[2],C[3]);
endmodule;

verilog/tests/mul_tb.v
`include "../modules/mul.v"

module mul_tb;
    reg [1:0] a=0;
    reg [1:0] b=0;
    wire [3:0] c;

    integer i;
    integer j;

    integer p;

    mul m(a,b,c);

    initial begin
        $dumpfile("../simulations/mul_sim.vcd");
        $dumpvars(1,mul_tb);

        for(i=0;i<4;i=i+1) begin;
            a = i; #1;
            for (j = 0;j<4;j=j+1) begin;
                b = j;
                p = a*b;
                #1;
                if (p!=c) begin
                    $display("%d * %d != %d",a,b,c);
                end
            end
        end
    end
endmodule;

verilog/simulations/mul_sim.vcd
$date
	Tue Oct 24 12:45:02 2023
$end
$version
	Icarus Verilog
$end
$timescale
	1s
$end
$scope module mul_tb $end
$var wire 4 ! c [3:0] $end
$var reg 2 " a [1:0] $end
$var reg 2 # b [1:0] $end
$var integer 32 $ i [31:0] $end
$var integer 32 % j [31:0] $end
$var integer 32 & p [31:0] $end
$upscope $end
$enddefinitions $end
$comment Show the parameter values. $end
$dumpall
$end
#0
$dumpvars
bx &
bx %
b0 $
b0 #
b0 "
b0 !
$end
#1
b0 &
b0 %
#2
b1 #
b1 %
#3
b10 #
b10 %
#4
b11 #
b11 %
#5
b11 !
b1 "
b1 $
b100 %
#6
b0 !
b0 #
b0 %
#7
b1 !
b1 &
b1 #
b1 %
#8
b10 !
b10 &
b10 #
b10 %
#9
b11 !
b11 &
b11 #
b11 %
#10
b110 !
b10 "
b10 $
b100 %
#11
b0 !
b0 &
b0 #
b0 %
#12
b10 !
b10 &
b1 #
b1 %
#13
b100 !
b100 &
b10 #
b10 %
#14
b110 !
b110 &
b11 #
b11 %
#15
b1001 !
b11 "
b11 $
b100 %
#16
b0 !
b0 &
b0 #
b0 %
#17
b11 !
b11 &
b1 #
b1 %
#18
b110 !
b110 &
b10 #
b10 %
#19
b1001 !
b1001 &
b11 #
b11 %
#20
b100 $
b100 %
