verilog/modules/mux.v
module mux (A,B,S,Y);
    input A, B, S;
    output Y;

    cmos(Y, A, S, ~S);
    cmos(Y, B, ~S, S);
endmodule;

verilog/tests/mux_tb.v
`include "./mux.v"
module mux_tb;
    reg a = 0;
    reg b = 0;
    reg s = 0;
    wire y;

    mux m1(a,b,s,y);

    initial begin
        $dumpfile("mux_sim.vcd");
        $dumpvars;

        a=0;b=0;s=0;
        #1 a=0;b=0;s=1;
        #1 a=0;b=1;s=0;
        #1 a=0;b=1;s=1;
        #1 a=1;b=0;s=0;
        #1 a=1;b=0;s=1;
        #1 a=1;b=1;s=0;
        #1 a=1;b=1;s=1;
        #1;
        
    end;

endmodule;

verilog/simulations/mux_sim.vcd
$date
	Mon Oct 23 15:27:41 2023
$end
$version
	Icarus Verilog
$end
$timescale
	1s
$end
$scope module mux_tb $end
$var wire 1 ! y $end
$var reg 1 " a $end
$var reg 1 # b $end
$var reg 1 $ s $end
$scope module m1 $end
$var wire 1 " A $end
$var wire 1 # B $end
$var wire 1 $ S $end
$var wire 1 ! Y $end
$upscope $end
$upscope $end
$enddefinitions $end
$comment Show the parameter values. $end
$dumpall
$end
#0
$dumpvars
0$
0#
0"
0!
$end
#1
1$
#2
1!
0$
1#
#3
0!
1$
#4
0$
0#
0!
1"
#5
1!
1$
#6
0$
1#
#7
1$
