verilog/modules/d_latch.v
module d_latch(
    input in,
    input clk,
    input clk_bar,
    output Q,
    output Q_bar);

    wire clk_bar,w;

    not(w,Q_bar);
    not(Q_bar,Q);
    cmos(Q,in,clk,clk_bar);
    cmos(Q,w,clk_bar,clk);
endmodule;

verilog/modules/d_flip_flop.v
`include "../modules/d_latch.v"

module d_flip_flop(
    input in,
    input clk,
    input clk_bar,
    output Q,
    output Q_bar);

    wire w1, w2, w3, w4;

    not(w1,in);
    d_latch d1(w1,clk_bar,clk,,w2);
    d_latch d2(w2,clk,clk_bar,w4,w3);
    not(Q,w3);
    buf(Q_bar,w4);
endmodule;

verilog/modules/mux.v
module mux (A,B,S,Y);
    input A, B, S;
    output Y;

    cmos(Y, A, S, ~S);
    cmos(Y, B, ~S, S);
endmodule;

verilog/modules/register.v
`include "../modules/mux.v"
`include "../modules/d_flip_flop.v"

module register(
    input in,
    input EN,
    input RST_bar,
    input CLK,
    input CLK_bar,
    output Q,
    output Q_bar);

    wire w1,w2;

    mux m1(in,Q,EN,w1);
    and(w2,w1,RST_bar);
    d_flip_flop d1(w2,CLK,CLK_bar,Q,Q_bar);
endmodule;

verilog/modules/register_8_bit.v
`include "../modules/register.v"

module register_8_bit(
    input [7:0] In,
    input EN,
    input RST_bar,
    input CLK,
    input CLK_bar,
    output [7:0] Q,
    output [7:0] Q_bar);

    register r0(In[0],EN,RST_bar,CLK,CLK_bar,Q[0],Q_bar[0]);
    register r1(In[1],EN,RST_bar,CLK,CLK_bar,Q[1],Q_bar[1]);
    register r2(In[2],EN,RST_bar,CLK,CLK_bar,Q[2],Q_bar[2]);
    register r3(In[3],EN,RST_bar,CLK,CLK_bar,Q[3],Q_bar[3]);
    register r4(In[4],EN,RST_bar,CLK,CLK_bar,Q[4],Q_bar[4]);
    register r5(In[5],EN,RST_bar,CLK,CLK_bar,Q[5],Q_bar[5]);
    register r6(In[6],EN,RST_bar,CLK,CLK_bar,Q[6],Q_bar[6]);
    register r7(In[7],EN,RST_bar,CLK,CLK_bar,Q[7],Q_bar[7]);
endmodule;

verilog/tests/register_8_bit_tb.v
`include "../modules/register_8_bit.v"

module register_8_bit_tb;
    reg [7:0] A;
    wire [7:0] Q;
    wire [7:0] Q_bar;

    reg EN = 0;

    reg RST = 0;
    wire RST_bar;
    assign RST_bar = ~RST;

    reg clk = 0;
    wire clk_bar;
    assign clk_bar = ~clk;
    always #1 clk = ~clk;

    register_8_bit r1(A,EN,RST_bar,clk,clk_bar,Q,Q_bar);

    integer i = 0;

    initial begin
        $dumpfile("../simulations/register_8_bit_sim.vcd");
        $dumpvars(1, register_8_bit_tb);
        wait(clk);
        wait(~clk);
        EN = 1;
        RST = 0;
        for(i=0;i<256;i=i+1) begin
            wait(clk);
            A = i;
            wait(~clk);
            wait(clk);
            wait(~clk);
            wait(clk);
            if(A!=Q) begin
                $display("%d != %d",A,Q);
            end;
            wait(~clk);
            wait(clk);
            wait(~clk);
        end;
        wait(clk);
        wait(~clk);
        RST = 0;
        A = 100;
        wait(~clk);
        wait(clk);
        wait(~clk);
        EN = 0;
        for(i=0;i<256;i=i+1) begin
            wait(clk);
            A = i;
            wait(~clk);
            wait(clk);
            wait(~clk);
            wait(clk);
            if(Q!=100) begin
                $display("ERROR: Write with EN = 0, Q = %d", Q);
            end;
            wait(~clk);
            wait(clk);
            wait(~clk);
        end;
        wait(clk);
        wait(~clk);
        EN = 0;
        RST = 1;
        for(i=0;i<256;i=i+1) begin
            wait(clk);
            A = i;
            wait(~clk);
            wait(clk);
            wait(~clk);
            wait(clk);
            if(Q!=0) begin
                $display("ERROR: Write with RST = 1, Q = %d", Q);
            end;
            wait(~clk);
            wait(clk);
            wait(~clk);
        end;
        wait(clk);
        wait(~clk);
        EN = 1;
        RST = 1;
        for(i=0;i<256;i=i+1) begin
            wait(clk);
            A = i;
            wait(~clk);
            wait(clk);
            wait(~clk);
            wait(clk);
            if(Q!=0) begin
                $display("ERROR: Write with RST = 1, Q = %d", Q);
            end;
            wait(~clk);
            wait(clk);
            wait(~clk);
        end;
        $finish();
    end;
endmodule;

verilog/simulations/register_8_bit_sim.vcd
$date
	Tue Oct 24 15:47:03 2023
$end
$version
	Icarus Verilog
$end
$timescale
	1s
$end
$scope module register_8_bit_tb $end
$var wire 1 ! RST_bar $end
$var wire 1 " clk_bar $end
$var wire 8 # Q_bar [7:0] $end
$var wire 8 $ Q [7:0] $end
$var reg 8 % A [7:0] $end
$var reg 1 & EN $end
$var reg 1 ' RST $end
$var reg 1 ( clk $end
$var integer 32 ) i [31:0] $end
$upscope $end
$enddefinitions $end
$comment Show the parameter values. $end
$dumpall
$end
#0
$dumpvars
b0 )
0(
0'
0&
bx %
bx $
bx #
1"
1!
$end
#1
0"
1(
#2
1&
1"
0(
#3
b0 %
0"
1(
#4
1"
0(
#5
b0 $
b0 #
0"
1(
#6
1"
0(
#7
0"
1(
#8
1"
0(
#9
0"
1(
#10
b1 )
1"
0(
#11
b1 %
0"
1(
#12
1"
0(
#13
b1 $
b1 #
0"
1(
#14
1"
0(
#15
0"
1(
#16
1"
0(
#17
0"
1(
#18
b10 )
1"
0(
#19
b10 %
0"
1(
#20
1"
0(
#21
b10 $
b10 #
0"
1(
#22
1"
0(
#23
0"
1(
#24
1"
0(
#25
0"
1(
#26
b11 )
1"
0(
#27
b11 %
0"
1(
#28
1"
0(
#29
b11 $
b11 #
0"
1(
#30
1"
0(
#31
0"
1(
#32
1"
0(
#33
0"
1(
#34
b100 )
1"
0(
#35
b100 %
0"
1(
#36
1"
0(
#37
b100 $
b100 #
0"
1(
#38
1"
0(
#39
0"
1(
#40
1"
0(
#41
0"
1(
#42
b101 )
1"
0(
#43
b101 %
0"
1(
#44
1"
0(
#45
b101 $
b101 #
0"
1(
#46
1"
0(
#47
0"
1(
#48
1"
0(
#49
0"
1(
#50
b110 )
1"
0(
#51
b110 %
0"
1(
#52
1"
0(
#53
b110 $
b110 #
0"
1(
#54
1"
0(
#55
0"
1(
#56
1"
0(
#57
0"
1(
#58
b111 )
1"
0(
#59
b111 %
0"
1(
#60
1"
0(
#61
b111 $
b111 #
0"
1(
#62
1"
0(
#63
0"
1(
#64
1"
0(
#65
0"
1(
#66
b1000 )
1"
0(
#67
b1000 %
0"
1(
#68
1"
0(
#69
b1000 $
b1000 #
0"
1(
#70
1"
0(
#71
0"
1(
#72
1"
0(
#73
0"
1(
#74
b1001 )
1"
0(
#75
b1001 %
0"
1(
#76
1"
0(
#77
b1001 $
b1001 #
0"
1(
#78
1"
0(
#79
0"
1(
#80
1"
0(
#81
0"
1(
#82
b1010 )
1"
0(
#83
b1010 %
0"
1(
#84
1"
0(
#85
b1010 $
b1010 #
0"
1(
#86
1"
0(
#87
0"
1(
#88
1"
0(
#89
0"
1(
#90
b1011 )
1"
0(
#91
b1011 %
0"
1(
#92
1"
0(
#93
b1011 $
b1011 #
0"
1(
#94
1"
0(
#95
0"
1(
#96
1"
0(
#97
0"
1(
#98
b1100 )
1"
0(
#99
b1100 %
0"
1(
#100
1"
0(
#101
b1100 $
b1100 #
0"
1(
#102
1"
0(
#103
0"
1(
#104
1"
0(
#105
0"
1(
#106
b1101 )
1"
0(
#107
b1101 %
0"
1(
#108
1"
0(
#109
b1101 $
b1101 #
0"
1(
#110
1"
0(
#111
0"
1(
#112
1"
0(
#113
0"
1(
#114
b1110 )
1"
0(
#115
b1110 %
0"
1(
#116
1"
0(
#117
b1110 $
b1110 #
0"
1(
#118
1"
0(
#119
0"
1(
#120
1"
0(
#121
0"
1(
#122
b1111 )
1"
0(
#123
b1111 %
0"
1(
#124
1"
0(
#125
b1111 $
b1111 #
0"
1(
#126
1"
0(
#127
0"
1(
#128
1"
0(
#129
0"
1(
#130
b10000 )
1"
0(
#131
b10000 %
0"
1(
#132
1"
0(
#133
b10000 $
b10000 #
0"
1(
#134
1"
0(
#135
0"
1(
#136
1"
0(
#137
0"
1(
#138
b10001 )
1"
0(
#139
b10001 %
0"
1(
#140
1"
0(
#141
b10001 $
b10001 #
0"
1(
#142
1"
0(
#143
0"
1(
#144
1"
0(
#145
0"
1(
#146
b10010 )
1"
0(
#147
b10010 %
0"
1(
#148
1"
0(
#149
b10010 $
b10010 #
0"
1(
#150
1"
0(
#151
0"
1(
#152
1"
0(
#153
0"
1(
#154
b10011 )
1"
0(
#155
b10011 %
0"
1(
#156
1"
0(
#157
b10011 $
b10011 #
0"
1(
#158
1"
0(
#159
0"
1(
#160
1"
0(
#161
0"
1(
#162
b10100 )
1"
0(
#163
b10100 %
0"
1(
#164
1"
0(
#165
b10100 $
b10100 #
0"
1(
#166
1"
0(
#167
0"
1(
#168
1"
0(
#169
0"
1(
#170
b10101 )
1"
0(
#171
b10101 %
0"
1(
#172
1"
0(
#173
b10101 $
b10101 #
0"
1(
#174
1"
0(
#175
0"
1(
#176
1"
0(
#177
0"
1(
#178
b10110 )
1"
0(
#179
b10110 %
0"
1(
#180
1"
0(
#181
b10110 $
b10110 #
0"
1(
#182
1"
0(
#183
0"
1(
#184
1"
0(
#185
0"
1(
#186
b10111 )
1"
0(
#187
b10111 %
0"
1(
#188
1"
0(
#189
b10111 $
b10111 #
0"
1(
#190
1"
0(
#191
0"
1(
#192
1"
0(
#193
0"
1(
#194
b11000 )
1"
0(
#195
b11000 %
0"
1(
#196
1"
0(
#197
b11000 $
b11000 #
0"
1(
#198
1"
0(
#199
0"
1(
#200
1"
0(
#201
0"
1(
#202
b11001 )
1"
0(
#203
b11001 %
0"
1(
#204
1"
0(
#205
b11001 $
b11001 #
0"
1(
#206
1"
0(
#207
0"
1(
#208
1"
0(
#209
0"
1(
#210
b11010 )
1"
0(
#211
b11010 %
0"
1(
#212
1"
0(
#213
b11010 $
b11010 #
0"
1(
#214
1"
0(
#215
0"
1(
#216
1"
0(
#217
0"
1(
#218
b11011 )
1"
0(
#219
b11011 %
0"
1(
#220
1"
0(
#221
b11011 $
b11011 #
0"
1(
#222
1"
0(
#223
0"
1(
#224
1"
0(
#225
0"
1(
#226
b11100 )
1"
0(
#227
b11100 %
0"
1(
#228
1"
0(
#229
b11100 $
b11100 #
0"
1(
#230
1"
0(
#231
0"
1(
#232
1"
0(
#233
0"
1(
#234
b11101 )
1"
0(
#235
b11101 %
0"
1(
#236
1"
0(
#237
b11101 $
b11101 #
0"
1(
#238
1"
0(
#239
0"
1(
#240
1"
0(
#241
0"
1(
#242
b11110 )
1"
0(
#243
b11110 %
0"
1(
#244
1"
0(
#245
b11110 $
b11110 #
0"
1(
#246
1"
0(
#247
0"
1(
#248
1"
0(
#249
0"
1(
#250
b11111 )
1"
0(
#251
b11111 %
0"
1(
#252
1"
0(
#253
b11111 $
b11111 #
0"
1(
#254
1"
0(
#255
0"
1(
#256
1"
0(
#257
0"
1(
#258
b100000 )
1"
0(
#259
b100000 %
0"
1(
#260
1"
0(
#261
b100000 $
b100000 #
0"
1(
#262
1"
0(
#263
0"
1(
#264
1"
0(
#265
0"
1(
#266
b100001 )
1"
0(
#267
b100001 %
0"
1(
#268
1"
0(
#269
b100001 $
b100001 #
0"
1(
#270
1"
0(
#271
0"
1(
#272
1"
0(
#273
0"
1(
#274
b100010 )
1"
0(
#275
b100010 %
0"
1(
#276
1"
0(
#277
b100010 $
b100010 #
0"
1(
#278
1"
0(
#279
0"
1(
#280
1"
0(
#281
0"
1(
#282
b100011 )
1"
0(
#283
b100011 %
0"
1(
#284
1"
0(
#285
b100011 $
b100011 #
0"
1(
#286
1"
0(
#287
0"
1(
#288
1"
0(
#289
0"
1(
#290
b100100 )
1"
0(
#291
b100100 %
0"
1(
#292
1"
0(
#293
b100100 $
b100100 #
0"
1(
#294
1"
0(
#295
0"
1(
#296
1"
0(
#297
0"
1(
#298
b100101 )
1"
0(
#299
b100101 %
0"
1(
#300
1"
0(
#301
b100101 $
b100101 #
0"
1(
#302
1"
0(
#303
0"
1(
#304
1"
0(
#305
0"
1(
#306
b100110 )
1"
0(
#307
b100110 %
0"
1(
#308
1"
0(
#309
b100110 $
b100110 #
0"
1(
#310
1"
0(
#311
0"
1(
#312
1"
0(
#313
0"
1(
#314
b100111 )
1"
0(
#315
b100111 %
0"
1(
#316
1"
0(
#317
b100111 $
b100111 #
0"
1(
#318
1"
0(
#319
0"
1(
#320
1"
0(
#321
0"
1(
#322
b101000 )
1"
0(
#323
b101000 %
0"
1(
#324
1"
0(
#325
b101000 $
b101000 #
0"
1(
#326
1"
0(
#327
0"
1(
#328
1"
0(
#329
0"
1(
#330
b101001 )
1"
0(
#331
b101001 %
0"
1(
#332
1"
0(
#333
b101001 $
b101001 #
0"
1(
#334
1"
0(
#335
0"
1(
#336
1"
0(
#337
0"
1(
#338
b101010 )
1"
0(
#339
b101010 %
0"
1(
#340
1"
0(
#341
b101010 $
b101010 #
0"
1(
#342
1"
0(
#343
0"
1(
#344
1"
0(
#345
0"
1(
#346
b101011 )
1"
0(
#347
b101011 %
0"
1(
#348
1"
0(
#349
b101011 $
b101011 #
0"
1(
#350
1"
0(
#351
0"
1(
#352
1"
0(
#353
0"
1(
#354
b101100 )
1"
0(
#355
b101100 %
0"
1(
#356
1"
0(
#357
b101100 $
b101100 #
0"
1(
#358
1"
0(
#359
0"
1(
#360
1"
0(
#361
0"
1(
#362
b101101 )
1"
0(
#363
b101101 %
0"
1(
#364
1"
0(
#365
b101101 $
b101101 #
0"
1(
#366
1"
0(
#367
0"
1(
#368
1"
0(
#369
0"
1(
#370
b101110 )
1"
0(
#371
b101110 %
0"
1(
#372
1"
0(
#373
b101110 $
b101110 #
0"
1(
#374
1"
0(
#375
0"
1(
#376
1"
0(
#377
0"
1(
#378
b101111 )
1"
0(
#379
b101111 %
0"
1(
#380
1"
0(
#381
b101111 $
b101111 #
0"
1(
#382
1"
0(
#383
0"
1(
#384
1"
0(
#385
0"
1(
#386
b110000 )
1"
0(
#387
b110000 %
0"
1(
#388
1"
0(
#389
b110000 $
b110000 #
0"
1(
#390
1"
0(
#391
0"
1(
#392
1"
0(
#393
0"
1(
#394
b110001 )
1"
0(
#395
b110001 %
0"
1(
#396
1"
0(
#397
b110001 $
b110001 #
0"
1(
#398
1"
0(
#399
0"
1(
#400
1"
0(
#401
0"
1(
#402
b110010 )
1"
0(
#403
b110010 %
0"
1(
#404
1"
0(
#405
b110010 $
b110010 #
0"
1(
#406
1"
0(
#407
0"
1(
#408
1"
0(
#409
0"
1(
#410
b110011 )
1"
0(
#411
b110011 %
0"
1(
#412
1"
0(
#413
b110011 $
b110011 #
0"
1(
#414
1"
0(
#415
0"
1(
#416
1"
0(
#417
0"
1(
#418
b110100 )
1"
0(
#419
b110100 %
0"
1(
#420
1"
0(
#421
b110100 $
b110100 #
0"
1(
#422
1"
0(
#423
0"
1(
#424
1"
0(
#425
0"
1(
#426
b110101 )
1"
0(
#427
b110101 %
0"
1(
#428
1"
0(
#429
b110101 $
b110101 #
0"
1(
#430
1"
0(
#431
0"
1(
#432
1"
0(
#433
0"
1(
#434
b110110 )
1"
0(
#435
b110110 %
0"
1(
#436
1"
0(
#437
b110110 $
b110110 #
0"
1(
#438
1"
0(
#439
0"
1(
#440
1"
0(
#441
0"
1(
#442
b110111 )
1"
0(
#443
b110111 %
0"
1(
#444
1"
0(
#445
b110111 $
b110111 #
0"
1(
#446
1"
0(
#447
0"
1(
#448
1"
0(
#449
0"
1(
#450
b111000 )
1"
0(
#451
b111000 %
0"
1(
#452
1"
0(
#453
b111000 $
b111000 #
0"
1(
#454
1"
0(
#455
0"
1(
#456
1"
0(
#457
0"
1(
#458
b111001 )
1"
0(
#459
b111001 %
0"
1(
#460
1"
0(
#461
b111001 $
b111001 #
0"
1(
#462
1"
0(
#463
0"
1(
#464
1"
0(
#465
0"
1(
#466
b111010 )
1"
0(
#467
b111010 %
0"
1(
#468
1"
0(
#469
b111010 $
b111010 #
0"
1(
#470
1"
0(
#471
0"
1(
#472
1"
0(
#473
0"
1(
#474
b111011 )
1"
0(
#475
b111011 %
0"
1(
#476
1"
0(
#477
b111011 $
b111011 #
0"
1(
#478
1"
0(
#479
0"
1(
#480
1"
0(
#481
0"
1(
#482
b111100 )
1"
0(
#483
b111100 %
0"
1(
#484
1"
0(
#485
b111100 $
b111100 #
0"
1(
#486
1"
0(
#487
0"
1(
#488
1"
0(
#489
0"
1(
#490
b111101 )
1"
0(
#491
b111101 %
0"
1(
#492
1"
0(
#493
b111101 $
b111101 #
0"
1(
#494
1"
0(
#495
0"
1(
#496
1"
0(
#497
0"
1(
#498
b111110 )
1"
0(
#499
b111110 %
0"
1(
#500
1"
0(
#501
b111110 $
b111110 #
0"
1(
#502
1"
0(
#503
0"
1(
#504
1"
0(
#505
0"
1(
#506
b111111 )
1"
0(
#507
b111111 %
0"
1(
#508
1"
0(
#509
b111111 $
b111111 #
0"
1(
#510
1"
0(
#511
0"
1(
#512
1"
0(
#513
0"
1(
#514
b1000000 )
1"
0(
#515
b1000000 %
0"
1(
#516
1"
0(
#517
b1000000 $
b1000000 #
0"
1(
#518
1"
0(
#519
0"
1(
#520
1"
0(
#521
0"
1(
#522
b1000001 )
1"
0(
#523
b1000001 %
0"
1(
#524
1"
0(
#525
b1000001 $
b1000001 #
0"
1(
#526
1"
0(
#527
0"
1(
#528
1"
0(
#529
0"
1(
#530
b1000010 )
1"
0(
#531
b1000010 %
0"
1(
#532
1"
0(
#533
b1000010 $
b1000010 #
0"
1(
#534
1"
0(
#535
0"
1(
#536
1"
0(
#537
0"
1(
#538
b1000011 )
1"
0(
#539
b1000011 %
0"
1(
#540
1"
0(
#541
b1000011 $
b1000011 #
0"
1(
#542
1"
0(
#543
0"
1(
#544
1"
0(
#545
0"
1(
#546
b1000100 )
1"
0(
#547
b1000100 %
0"
1(
#548
1"
0(
#549
b1000100 $
b1000100 #
0"
1(
#550
1"
0(
#551
0"
1(
#552
1"
0(
#553
0"
1(
#554
b1000101 )
1"
0(
#555
b1000101 %
0"
1(
#556
1"
0(
#557
b1000101 $
b1000101 #
0"
1(
#558
1"
0(
#559
0"
1(
#560
1"
0(
#561
0"
1(
#562
b1000110 )
1"
0(
#563
b1000110 %
0"
1(
#564
1"
0(
#565
b1000110 $
b1000110 #
0"
1(
#566
1"
0(
#567
0"
1(
#568
1"
0(
#569
0"
1(
#570
b1000111 )
1"
0(
#571
b1000111 %
0"
1(
#572
1"
0(
#573
b1000111 $
b1000111 #
0"
1(
#574
1"
0(
#575
0"
1(
#576
1"
0(
#577
0"
1(
#578
b1001000 )
1"
0(
#579
b1001000 %
0"
1(
#580
1"
0(
#581
b1001000 $
b1001000 #
0"
1(
#582
1"
0(
#583
0"
1(
#584
1"
0(
#585
0"
1(
#586
b1001001 )
1"
0(
#587
b1001001 %
0"
1(
#588
1"
0(
#589
b1001001 $
b1001001 #
0"
1(
#590
1"
0(
#591
0"
1(
#592
1"
0(
#593
0"
1(
#594
b1001010 )
1"
0(
#595
b1001010 %
0"
1(
#596
1"
0(
#597
b1001010 $
b1001010 #
0"
1(
#598
1"
0(
#599
0"
1(
#600
1"
0(
#601
0"
1(
#602
b1001011 )
1"
0(
#603
b1001011 %
0"
1(
#604
1"
0(
#605
b1001011 $
b1001011 #
0"
1(
#606
1"
0(
#607
0"
1(
#608
1"
0(
#609
0"
1(
#610
b1001100 )
1"
0(
#611
b1001100 %
0"
1(
#612
1"
0(
#613
b1001100 $
b1001100 #
0"
1(
#614
1"
0(
#615
0"
1(
#616
1"
0(
#617
0"
1(
#618
b1001101 )
1"
0(
#619
b1001101 %
0"
1(
#620
1"
0(
#621
b1001101 $
b1001101 #
0"
1(
#622
1"
0(
#623
0"
1(
#624
1"
0(
#625
0"
1(
#626
b1001110 )
1"
0(
#627
b1001110 %
0"
1(
#628
1"
0(
#629
b1001110 $
b1001110 #
0"
1(
#630
1"
0(
#631
0"
1(
#632
1"
0(
#633
0"
1(
#634
b1001111 )
1"
0(
#635
b1001111 %
0"
1(
#636
1"
0(
#637
b1001111 $
b1001111 #
0"
1(
#638
1"
0(
#639
0"
1(
#640
1"
0(
#641
0"
1(
#642
b1010000 )
1"
0(
#643
b1010000 %
0"
1(
#644
1"
0(
#645
b1010000 $
b1010000 #
0"
1(
#646
1"
0(
#647
0"
1(
#648
1"
0(
#649
0"
1(
#650
b1010001 )
1"
0(
#651
b1010001 %
0"
1(
#652
1"
0(
#653
b1010001 $
b1010001 #
0"
1(
#654
1"
0(
#655
0"
1(
#656
1"
0(
#657
0"
1(
#658
b1010010 )
1"
0(
#659
b1010010 %
0"
1(
#660
1"
0(
#661
b1010010 $
b1010010 #
0"
1(
#662
1"
0(
#663
0"
1(
#664
1"
0(
#665
0"
1(
#666
b1010011 )
1"
0(
#667
b1010011 %
0"
1(
#668
1"
0(
#669
b1010011 $
b1010011 #
0"
1(
#670
1"
0(
#671
0"
1(
#672
1"
0(
#673
0"
1(
#674
b1010100 )
1"
0(
#675
b1010100 %
0"
1(
#676
1"
0(
#677
b1010100 $
b1010100 #
0"
1(
#678
1"
0(
#679
0"
1(
#680
1"
0(
#681
0"
1(
#682
b1010101 )
1"
0(
#683
b1010101 %
0"
1(
#684
1"
0(
#685
b1010101 $
b1010101 #
0"
1(
#686
1"
0(
#687
0"
1(
#688
1"
0(
#689
0"
1(
#690
b1010110 )
1"
0(
#691
b1010110 %
0"
1(
#692
1"
0(
#693
b1010110 $
b1010110 #
0"
1(
#694
1"
0(
#695
0"
1(
#696
1"
0(
#697
0"
1(
#698
b1010111 )
1"
0(
#699
b1010111 %
0"
1(
#700
1"
0(
#701
b1010111 $
b1010111 #
0"
1(
#702
1"
0(
#703
0"
1(
#704
1"
0(
#705
0"
1(
#706
b1011000 )
1"
0(
#707
b1011000 %
0"
1(
#708
1"
0(
#709
b1011000 $
b1011000 #
0"
1(
#710
1"
0(
#711
0"
1(
#712
1"
0(
#713
0"
1(
#714
b1011001 )
1"
0(
#715
b1011001 %
0"
1(
#716
1"
0(
#717
b1011001 $
b1011001 #
0"
1(
#718
1"
0(
#719
0"
1(
#720
1"
0(
#721
0"
1(
#722
b1011010 )
1"
0(
#723
b1011010 %
0"
1(
#724
1"
0(
#725
b1011010 $
b1011010 #
0"
1(
#726
1"
0(
#727
0"
1(
#728
1"
0(
#729
0"
1(
#730
b1011011 )
1"
0(
#731
b1011011 %
0"
1(
#732
1"
0(
#733
b1011011 $
b1011011 #
0"
1(
#734
1"
0(
#735
0"
1(
#736
1"
0(
#737
0"
1(
#738
b1011100 )
1"
0(
#739
b1011100 %
0"
1(
#740
1"
0(
#741
b1011100 $
b1011100 #
0"
1(
#742
1"
0(
#743
0"
1(
#744
1"
0(
#745
0"
1(
#746
b1011101 )
1"
0(
#747
b1011101 %
0"
1(
#748
1"
0(
#749
b1011101 $
b1011101 #
0"
1(
#750
1"
0(
#751
0"
1(
#752
1"
0(
#753
0"
1(
#754
b1011110 )
1"
0(
#755
b1011110 %
0"
1(
#756
1"
0(
#757
b1011110 $
b1011110 #
0"
1(
#758
1"
0(
#759
0"
1(
#760
1"
0(
#761
0"
1(
#762
b1011111 )
1"
0(
#763
b1011111 %
0"
1(
#764
1"
0(
#765
b1011111 $
b1011111 #
0"
1(
#766
1"
0(
#767
0"
1(
#768
1"
0(
#769
0"
1(
#770
b1100000 )
1"
0(
#771
b1100000 %
0"
1(
#772
1"
0(
#773
b1100000 $
b1100000 #
0"
1(
#774
1"
0(
#775
0"
1(
#776
1"
0(
#777
0"
1(
#778
b1100001 )
1"
0(
#779
b1100001 %
0"
1(
#780
1"
0(
#781
b1100001 $
b1100001 #
0"
1(
#782
1"
0(
#783
0"
1(
#784
1"
0(
#785
0"
1(
#786
b1100010 )
1"
0(
#787
b1100010 %
0"
1(
#788
1"
0(
#789
b1100010 $
b1100010 #
0"
1(
#790
1"
0(
#791
0"
1(
#792
1"
0(
#793
0"
1(
#794
b1100011 )
1"
0(
#795
b1100011 %
0"
1(
#796
1"
0(
#797
b1100011 $
b1100011 #
0"
1(
#798
1"
0(
#799
0"
1(
#800
1"
0(
#801
0"
1(
#802
b1100100 )
1"
0(
#803
b1100100 %
0"
1(
#804
1"
0(
#805
b1100100 $
b1100100 #
0"
1(
#806
1"
0(
#807
0"
1(
#808
1"
0(
#809
0"
1(
#810
b1100101 )
1"
0(
#811
b1100101 %
0"
1(
#812
1"
0(
#813
b1100101 $
b1100101 #
0"
1(
#814
1"
0(
#815
0"
1(
#816
1"
0(
#817
0"
1(
#818
b1100110 )
1"
0(
#819
b1100110 %
0"
1(
#820
1"
0(
#821
b1100110 $
b1100110 #
0"
1(
#822
1"
0(
#823
0"
1(
#824
1"
0(
#825
0"
1(
#826
b1100111 )
1"
0(
#827
b1100111 %
0"
1(
#828
1"
0(
#829
b1100111 $
b1100111 #
0"
1(
#830
1"
0(
#831
0"
1(
#832
1"
0(
#833
0"
1(
#834
b1101000 )
1"
0(
#835
b1101000 %
0"
1(
#836
1"
0(
#837
b1101000 $
b1101000 #
0"
1(
#838
1"
0(
#839
0"
1(
#840
1"
0(
#841
0"
1(
#842
b1101001 )
1"
0(
#843
b1101001 %
0"
1(
#844
1"
0(
#845
b1101001 $
b1101001 #
0"
1(
#846
1"
0(
#847
0"
1(
#848
1"
0(
#849
0"
1(
#850
b1101010 )
1"
0(
#851
b1101010 %
0"
1(
#852
1"
0(
#853
b1101010 $
b1101010 #
0"
1(
#854
1"
0(
#855
0"
1(
#856
1"
0(
#857
0"
1(
#858
b1101011 )
1"
0(
#859
b1101011 %
0"
1(
#860
1"
0(
#861
b1101011 $
b1101011 #
0"
1(
#862
1"
0(
#863
0"
1(
#864
1"
0(
#865
0"
1(
#866
b1101100 )
1"
0(
#867
b1101100 %
0"
1(
#868
1"
0(
#869
b1101100 $
b1101100 #
0"
1(
#870
1"
0(
#871
0"
1(
#872
1"
0(
#873
0"
1(
#874
b1101101 )
1"
0(
#875
b1101101 %
0"
1(
#876
1"
0(
#877
b1101101 $
b1101101 #
0"
1(
#878
1"
0(
#879
0"
1(
#880
1"
0(
#881
0"
1(
#882
b1101110 )
1"
0(
#883
b1101110 %
0"
1(
#884
1"
0(
#885
b1101110 $
b1101110 #
0"
1(
#886
1"
0(
#887
0"
1(
#888
1"
0(
#889
0"
1(
#890
b1101111 )
1"
0(
#891
b1101111 %
0"
1(
#892
1"
0(
#893
b1101111 $
b1101111 #
0"
1(
#894
1"
0(
#895
0"
1(
#896
1"
0(
#897
0"
1(
#898
b1110000 )
1"
0(
#899
b1110000 %
0"
1(
#900
1"
0(
#901
b1110000 $
b1110000 #
0"
1(
#902
1"
0(
#903
0"
1(
#904
1"
0(
#905
0"
1(
#906
b1110001 )
1"
0(
#907
b1110001 %
0"
1(
#908
1"
0(
#909
b1110001 $
b1110001 #
0"
1(
#910
1"
0(
#911
0"
1(
#912
1"
0(
#913
0"
1(
#914
b1110010 )
1"
0(
#915
b1110010 %
0"
1(
#916
1"
0(
#917
b1110010 $
b1110010 #
0"
1(
#918
1"
0(
#919
0"
1(
#920
1"
0(
#921
0"
1(
#922
b1110011 )
1"
0(
#923
b1110011 %
0"
1(
#924
1"
0(
#925
b1110011 $
b1110011 #
0"
1(
#926
1"
0(
#927
0"
1(
#928
1"
0(
#929
0"
1(
#930
b1110100 )
1"
0(
#931
b1110100 %
0"
1(
#932
1"
0(
#933
b1110100 $
b1110100 #
0"
1(
#934
1"
0(
#935
0"
1(
#936
1"
0(
#937
0"
1(
#938
b1110101 )
1"
0(
#939
b1110101 %
0"
1(
#940
1"
0(
#941
b1110101 $
b1110101 #
0"
1(
#942
1"
0(
#943
0"
1(
#944
1"
0(
#945
0"
1(
#946
b1110110 )
1"
0(
#947
b1110110 %
0"
1(
#948
1"
0(
#949
b1110110 $
b1110110 #
0"
1(
#950
1"
0(
#951
0"
1(
#952
1"
0(
#953
0"
1(
#954
b1110111 )
1"
0(
#955
b1110111 %
0"
1(
#956
1"
0(
#957
b1110111 $
b1110111 #
0"
1(
#958
1"
0(
#959
0"
1(
#960
1"
0(
#961
0"
1(
#962
b1111000 )
1"
0(
#963
b1111000 %
0"
1(
#964
1"
0(
#965
b1111000 $
b1111000 #
0"
1(
#966
1"
0(
#967
0"
1(
#968
1"
0(
#969
0"
1(
#970
b1111001 )
1"
0(
#971
b1111001 %
0"
1(
#972
1"
0(
#973
b1111001 $
b1111001 #
0"
1(
#974
1"
0(
#975
0"
1(
#976
1"
0(
#977
0"
1(
#978
b1111010 )
1"
0(
#979
b1111010 %
0"
1(
#980
1"
0(
#981
b1111010 $
b1111010 #
0"
1(
#982
1"
0(
#983
0"
1(
#984
1"
0(
#985
0"
1(
#986
b1111011 )
1"
0(
#987
b1111011 %
0"
1(
#988
1"
0(
#989
b1111011 $
b1111011 #
0"
1(
#990
1"
0(
#991
0"
1(
#992
1"
0(
#993
0"
1(
#994
b1111100 )
1"
0(
#995
b1111100 %
0"
1(
#996
1"
0(
#997
b1111100 $
b1111100 #
0"
1(
#998
1"
0(
#999
0"
1(
#1000
1"
0(
#1001
0"
1(
#1002
b1111101 )
1"
0(
#1003
b1111101 %
0"
1(
#1004
1"
0(
#1005
b1111101 $
b1111101 #
0"
1(
#1006
1"
0(
#1007
0"
1(
#1008
1"
0(
#1009
0"
1(
#1010
b1111110 )
1"
0(
#1011
b1111110 %
0"
1(
#1012
1"
0(
#1013
b1111110 $
b1111110 #
0"
1(
#1014
1"
0(
#1015
0"
1(
#1016
1"
0(
#1017
0"
1(
#1018
b1111111 )
1"
0(
#1019
b1111111 %
0"
1(
#1020
1"
0(
#1021
b1111111 $
b1111111 #
0"
1(
#1022
1"
0(
#1023
0"
1(
#1024
1"
0(
#1025
0"
1(
#1026
b10000000 )
1"
0(
#1027
b10000000 %
0"
1(
#1028
1"
0(
