verilog/modules/d_latch.v
module d_latch(
    input in,
    input clk,
    input clk_bar,
    output Q,
    output Q_bar);

    wire clk_bar,w;

    not(w,Q_bar);
    not(Q_bar,Q);
    cmos(Q,in,clk,clk_bar);
    cmos(Q,w,clk_bar,clk);
endmodule;

verilog/modules/d_flip_flop.v
`include "../modules/d_latch.v"

module d_flip_flop(
    input in,
    input clk,
    input clk_bar,
    output Q,
    output Q_bar);

    wire w1, w2, w3, w4;

    not(w1,in);
    d_latch d1(w1,clk_bar,clk,,w2);
    d_latch d2(w2,clk,clk_bar,w4,w3);
    not(Q,w3);
    buf(Q_bar,w4);
endmodule;

verilog/modules/mux.v
module mux (A,B,S,Y);
    input A, B, S;
    output Y;
    wire Sbar;

    cmos(Y, A, S, ~S);
    cmos(Y, B, ~S, S);
endmodule;

verilog/modules/register.v
`include "../modules/mux.v"
`include "../modules/d_flip_flop.v"

module register(
    input in,
    input EN,
    input RST_bar,
    input CLK,
    input CLK_bar,
    output Q,
    output Q_bar);

    wire w1,w2;

    mux m1(in,Q,EN,w1);
    and(w2,w1,RST_bar);
    d_flip_flop d1(w2,CLK,CLK_bar,Q,Q_bar);
endmodule;

verilog/tests/register_tb.v
`include "../modules/register.v"

module register_tb;
    reg A;
    wire Q;
    wire Q_bar;

    reg EN = 0;
    reg RST = 0;
    wire RST_bar;
    assign RST_bar = ~RST;

    reg clk = 0;
    wire clk_bar;
    assign clk_bar = ~clk;
    always #1 clk = ~clk;

    register r1(A,EN,RST_bar,clk,clk_bar,Q,Q_bar);

    initial begin
        $dumpfile("../simulations/register_sim.vcd");
        $dumpvars(0, register_tb);

        #10; A = 1;
        #10; A = 0;
        #10; A = 1;
        #10; EN = 1;
        #10; A = 0;
        #10; A = 1;
        #10; A = 0;
        #10; A = 1;
        #10; EN = 0;
        #10; A = 0;
        #10; A = 1;
        #10; A = 0;
        #10; EN = 1;
        #10; A = 1;
        #10; A = 0;
        #10; A = 1;
        #10; EN = 0;
        #10; A = 0;
        #10; A = 1;
        #10; RST = 1;
        #10; EN = 1;
        #10; A = 0;
        #10; RST = 0;
        #10; A = 1;
        $finish();
    end;

endmodule;

verilog/simulations/register_sim.vcd
$date
	Tue Oct 24 15:01:05 2023
$end
$version
	Icarus Verilog
$end
$timescale
	1s
$end
$scope module register_tb $end
$var wire 1 ! RST_bar $end
$var wire 1 " clk_bar $end
$var wire 1 # Q_bar $end
$var wire 1 $ Q $end
$var reg 1 % A $end
$var reg 1 & EN $end
$var reg 1 ' RST $end
$var reg 1 ( clk $end
$scope module r1 $end
$var wire 1 ( CLK $end
$var wire 1 " CLK_bar $end
$var wire 1 & EN $end
$var wire 1 ! RST_bar $end
$var wire 1 % in $end
$var wire 1 ) w1 $end
$var wire 1 * w2 $end
$var wire 1 # Q_bar $end
$var wire 1 $ Q $end
$scope module d1 $end
$var wire 1 $ Q $end
$var wire 1 # Q_bar $end
$var wire 1 ( clk $end
$var wire 1 " clk_bar $end
$var wire 1 * in $end
$var wire 1 + w1 $end
$var wire 1 , w4 $end
$var wire 1 - w3 $end
$var wire 1 . w2 $end
$scope module d1 $end
$var wire 1 / Q $end
$var wire 1 . Q_bar $end
$var wire 1 " clk $end
$var wire 1 ( clk_bar $end
$var wire 1 + in $end
$var wire 1 0 w $end
$upscope $end
$scope module d2 $end
$var wire 1 , Q $end
$var wire 1 - Q_bar $end
$var wire 1 ( clk $end
$var wire 1 " clk_bar $end
$var wire 1 . in $end
$var wire 1 1 w $end
$upscope $end
$upscope $end
$scope module m1 $end
$var wire 1 % A $end
$var wire 1 $ B $end
$var wire 1 & S $end
$var wire 1 ) Y $end
$upscope $end
$upscope $end
$upscope $end
$enddefinitions $end
$comment Show the parameter values. $end
$dumpall
$end
#0
$dumpvars
x1
x0
x/
x.
x-
x,
x+
x*
x)
0(
0'
0&
x%
x$
x#
1"
1!
$end
#1
0"
1(
#2
1"
0(
#3
0"
1(
#4
1"
0(
#5
0"
1(
#6
1"
0(
#7
0"
1(
#8
1"
0(
#9
0"
1(
#10
1"
0(
1%
#11
0"
1(
#12
1"
0(
#13
0"
1(
#14
1"
0(
#15
0"
1(
#16
1"
0(
#17
0"
1(
#18
1"
0(
#19
0"
1(
#20
1"
0(
0%
#21
0"
1(
#22
1"
0(
#23
0"
1(
#24
1"
0(
#25
0"
1(
#26
1"
0(
#27
0"
1(
#28
1"
0(
#29
0"
1(
#30
1"
0(
1%
#31
0"
1(
#32
1"
0(
#33
0"
1(
#34
1"
0(
#35
0"
1(
#36
1"
0(
#37
0"
1(
#38
1"
0(
#39
0"
1(
#40
00
1.
0/
0+
1*
1"
1)
0(
1&
#41
11
1$
1#
0-
1,
0"
1(
#42
1"
0(
#43
0"
1(
#44
1"
0(
#45
0"
1(
#46
1"
0(
#47
0"
1(
#48
1"
0(
#49
0"
1(
#50
10
0.
1/
1+
1"
0*
0(
0)
0%
#51
01
0$
0#
1-
0"
0,
1(
#52
1"
0(
#53
0"
1(
#54
1"
0(
#55
0"
1(
#56
1"
0(
#57
0"
1(
#58
1"
0(
#59
0"
1(
#60
00
1.
0/
0+
1"
1*
0(
1)
1%
#61
11
1$
1#
0-
0"
1,
1(
#62
1"
0(
#63
0"
1(
#64
1"
0(
#65
0"
1(
#66
1"
0(
#67
0"
1(
#68
1"
0(
#69
0"
1(
#70
10
0.
1/
1+
1"
0*
0(
0)
0%
#71
01
0$
0#
1-
0"
0,
1(
#72
1"
0(
#73
0"
1(
#74
1"
0(
#75
0"
1(
#76
1"
0(
#77
0"
1(
#78
1"
0(
#79
0"
1(
#80
00
1.
0/
0+
1"
1*
0(
1)
1%
#81
11
1$
1#
0-
0"
1,
1(
#82
1"
0(
#83
0"
1(
#84
1"
0(
#85
0"
1(
#86
1"
0(
#87
0"
1(
#88
1"
0(
#89
0"
1(
#90
1"
0(
0&
#91
0"
1(
#92
1"
0(
#93
0"
1(
#94
1"
0(
#95
0"
1(
#96
1"
0(
#97
0"
1(
#98
1"
0(
#99
0"
1(
#100
1"
0(
0%
#101
0"
1(
#102
1"
0(
#103
0"
1(
#104
1"
0(
#105
0"
1(
#106
1"
0(
#107
0"
1(
#108
1"
0(
#109
0"
1(
#110
1"
0(
1%
#111
0"
1(
#112
1"
0(
#113
0"
1(
#114
1"
0(
#115
0"
1(
#116
1"
0(
#117
0"
1(
#118
1"
0(
#119
0"
1(
#120
1"
0(
0%
#121
0"
1(
#122
1"
0(
#123
0"
1(
#124
1"
0(
#125
0"
1(
#126
1"
0(
#127
0"
1(
#128
1"
0(
#129
0"
1(
#130
10
0.
1/
1+
1"
0*
0(
0)
1&
#131
01
0$
0#
1-
0"
0,
1(
#132
1"
0(
#133
0"
1(
#134
1"
0(
#135
0"
1(
#136
1"
0(
#137
0"
1(
#138
1"
0(
#139
0"
1(
#140
00
1.
0/
0+
1"
1*
0(
1)
1%
#141
11
1$
1#
0-
0"
1,
1(
#142
1"
0(
#143
0"
1(
#144
1"
0(
#145
0"
1(
#146
1"
0(
#147
0"
1(
#148
1"
0(
#149
0"
1(
#150
10
0.
1/
1+
1"
0*
0(
0)
0%
#151
01
0$
0#
1-
0"
0,
1(
#152
1"
0(
#153
0"
1(
#154
1"
0(
#155
0"
1(
#156
1"
0(
#157
0"
1(
#158
1"
0(
#159
0"
1(
#160
00
1.
0/
0+
1"
1*
0(
1)
1%
#161
11
1$
1#
0-
0"
1,
1(
#162
1"
0(
#163
0"
1(
#164
1"
0(
#165
0"
1(
#166
1"
0(
#167
0"
1(
#168
1"
0(
#169
0"
1(
#170
1"
0(
0&
#171
0"
1(
#172
1"
0(
#173
0"
1(
#174
1"
0(
#175
0"
1(
#176
1"
0(
#177
0"
1(
#178
1"
0(
#179
0"
1(
#180
1"
0(
0%
#181
0"
1(
#182
1"
0(
#183
0"
1(
#184
1"
0(
#185
0"
1(
#186
1"
0(
#187
0"
1(
#188
1"
0(
#189
0"
1(
#190
1"
0(
1%
#191
0"
1(
#192
1"
0(
#193
0"
1(
#194
1"
0(
#195
0"
1(
#196
1"
0(
#197
0"
1(
#198
1"
0(
#199
0"
1(
#200
10
0.
1/
1+
0*
1"
0!
0(
1'
#201
01
0)
0$
0#
1-
0"
0,
1(
#202
1"
0(
#203
0"
1(
#204
1"
0(
#205
0"
1(
#206
1"
0(
#207
0"
1(
#208
1"
0(
#209
0"
1(
#210
1"
0(
1)
1&
#211
0"
1(
#212
1"
0(
#213
0"
1(
#214
1"
0(
#215
0"
1(
#216
1"
0(
#217
0"
1(
#218
1"
0(
#219
0"
1(
#220
1"
0(
0)
0%
#221
0"
1(
#222
1"
0(
#223
0"
1(
#224
1"
0(
#225
0"
1(
#226
1"
0(
#227
0"
1(
#228
1"
0(
#229
0"
1(
#230
1"
1!
0(
0'
#231
0"
1(
#232
1"
0(
#233
0"
1(
#234
1"
0(
#235
0"
1(
#236
1"
0(
#237
0"
1(
#238
1"
0(
#239
0"
1(
#240
00
1.
0/
0+
1"
1*
0(
1)
1%
